{"cols":[{"type":"string"},{"type":"number"}],"rows":[{"c":[{"v":"11"},{"v":6.755931848}]},{"c":[{"v":"11"},{"v":6.747070352}]},{"c":[{"v":"11"},{"v":6.789375312}]},{"c":[{"v":"11"},{"v":6.753349736}]},{"c":[{"v":"11"},{"v":6.822867912}]},{"c":[{"v":"11"},{"v":6.824345168}]},{"c":[{"v":"11"},{"v":6.932791736}]},{"c":[{"v":"11"},{"v":6.76080016}]},{"c":[{"v":"11"},{"v":6.482863304}]},{"c":[{"v":"11"},{"v":6.460027656}]},{"c":[{"v":"11"},{"v":6.531814608}]},{"c":[{"v":"12"},{"v":6.606237488}]},{"c":[{"v":"12"},{"v":6.769988704}]},{"c":[{"v":"12"},{"v":6.849922944}]},{"c":[{"v":"12"},{"v":6.576933256}]},{"c":[{"v":"12"},{"v":6.917277024}]},{"c":[{"v":"12"},{"v":6.666986448}]},{"c":[{"v":"12"},{"v":6.775925064}]},{"c":[{"v":"12"},{"v":6.768679912}]},{"c":[{"v":"12"},{"v":6.641250504}]},{"c":[{"v":"12"},{"v":6.745173416}]},{"c":[{"v":"12"},{"v":6.580171752}]},{"c":[{"v":"12"},{"v":6.565359744}]},{"c":[{"v":"13"},{"v":6.664881376}]},{"c":[{"v":"13"},{"v":6.71970764}]},{"c":[{"v":"13"},{"v":6.765197728}]},{"c":[{"v":"13"},{"v":6.805481296}]},{"c":[{"v":"13"},{"v":6.729229728}]},{"c":[{"v":"13"},{"v":6.622288896}]},{"c":[{"v":"13"},{"v":6.526899376}]},{"c":[{"v":"13"},{"v":6.859657584}]},{"c":[{"v":"13"},{"v":6.790034184}]},{"c":[{"v":"13"},{"v":6.888029472}]},{"c":[{"v":"13"},{"v":6.71439216}]},{"c":[{"v":"13"},{"v":6.721229832}]},{"c":[{"v":"14"},{"v":6.895069888}]},{"c":[{"v":"14"},{"v":6.620872328}]},{"c":[{"v":"14"},{"v":6.94815684}]},{"c":[{"v":"14"},{"v":6.802308648}]},{"c":[{"v":"14"},{"v":6.785300408}]},{"c":[{"v":"14"},{"v":6.802292824}]},{"c":[{"v":"14"},{"v":6.728215336}]},{"c":[{"v":"14"},{"v":6.700244448}]},{"c":[{"v":"14"},{"v":6.689627832}]},{"c":[{"v":"14"},{"v":6.872651936}]},{"c":[{"v":"14"},{"v":6.81758964}]},{"c":[{"v":"14"},{"v":6.866451616}]},{"c":[{"v":"15"},{"v":7.131781568}]},{"c":[{"v":"15"},{"v":7.030091816}]},{"c":[{"v":"15"},{"v":6.967281648}]},{"c":[{"v":"15"},{"v":7.04010196}]},{"c":[{"v":"15"},{"v":7.06472544}]},{"c":[{"v":"15"},{"v":6.86977896}]},{"c":[{"v":"15"},{"v":6.735133048}]},{"c":[{"v":"15"},{"v":6.98559948}]},{"c":[{"v":"15"},{"v":6.664372512}]},{"c":[{"v":"15"},{"v":7.012023528}]},{"c":[{"v":"15"},{"v":6.983540824}]},{"c":[{"v":"15"},{"v":6.733662184}]},{"c":[{"v":"16"},{"v":6.671713576}]},{"c":[{"v":"16"},{"v":6.76663948}]},{"c":[{"v":"16"},{"v":6.706081464}]},{"c":[{"v":"16"},{"v":6.896266584}]},{"c":[{"v":"16"},{"v":7.024474864}]},{"c":[{"v":"16"},{"v":7.035066928}]},{"c":[{"v":"16"},{"v":7.434075112}]},{"c":[{"v":"16"},{"v":7.382629512}]},{"c":[{"v":"16"},{"v":7.505637464}]},{"c":[{"v":"16"},{"v":7.256785624}]},{"c":[{"v":"16"},{"v":7.509935168}]},{"c":[{"v":"16"},{"v":7.595663064}]},{"c":[{"v":"17"},{"v":7.694522208}]},{"c":[{"v":"17"},{"v":7.775872464}]},{"c":[{"v":"17"},{"v":7.590827736}]},{"c":[{"v":"17"},{"v":7.710152648}]},{"c":[{"v":"17"},{"v":7.647673208}]},{"c":[{"v":"17"},{"v":7.691499016}]},{"c":[{"v":"17"},{"v":7.90722436}]},{"c":[{"v":"17"},{"v":7.706634888}]},{"c":[{"v":"17"},{"v":7.53654288}]},{"c":[{"v":"17"},{"v":7.774319672}]},{"c":[{"v":"17"},{"v":8.236428288}]},{"c":[{"v":"17"},{"v":8.36595856}]},{"c":[{"v":"18"},{"v":8.162778872}]},{"c":[{"v":"18"},{"v":8.419716648}]},{"c":[{"v":"18"},{"v":8.608253712}]},{"c":[{"v":"18"},{"v":8.758467288}]},{"c":[{"v":"18"},{"v":8.877496}]},{"c":[{"v":"18"},{"v":8.825812296}]},{"c":[{"v":"18"},{"v":8.484527}]},{"c":[{"v":"18"},{"v":8.599843456}]},{"c":[{"v":"18"},{"v":8.61502116}]},{"c":[{"v":"18"},{"v":8.609646464}]},{"c":[{"v":"18"},{"v":8.637201152}]},{"c":[{"v":"18"},{"v":8.822466352}]},{"c":[{"v":"19"},{"v":9.066776032}]},{"c":[{"v":"19"},{"v":9.386924664}]},{"c":[{"v":"19"},{"v":9.419140936}]},{"c":[{"v":"19"},{"v":9.675756744}]},{"c":[{"v":"19"},{"v":9.731049304}]},{"c":[{"v":"19"},{"v":9.779304056}]},{"c":[{"v":"19"},{"v":9.422703288}]},{"c":[{"v":"19"},{"v":9.572603264}]},{"c":[{"v":"19"},{"v":9.745991824}]},{"c":[{"v":"19"},{"v":9.800248856}]},{"c":[{"v":"19"},{"v":9.74275136}]},{"c":[{"v":"19"},{"v":9.791667848}]},{"c":[{"v":"20"},{"v":10.0579864}]},{"c":[{"v":"20"},{"v":10.264475352}]},{"c":[{"v":"20"},{"v":10.206108176}]},{"c":[{"v":"20"},{"v":10.00580152}]},{"c":[{"v":"20"},{"v":9.753695832}]},{"c":[{"v":"20"},{"v":9.834352656}]},{"c":[{"v":"20"},{"v":9.713447024}]},{"c":[{"v":"20"},{"v":9.826279432}]},{"c":[{"v":"20"},{"v":9.914860472}]},{"c":[{"v":"20"},{"v":9.881557224}]},{"c":[{"v":"20"},{"v":9.981630376}]},{"c":[{"v":"20"},{"v":10.03857748}]},{"c":[{"v":"21"},{"v":10.140375616}]},{"c":[{"v":"21"},{"v":9.919000704}]},{"c":[{"v":"21"},{"v":9.86124276}]},{"c":[{"v":"21"},{"v":9.714645456}]},{"c":[{"v":"21"},{"v":9.779329792}]},{"c":[{"v":"21"},{"v":9.663596896}]},{"c":[{"v":"21"},{"v":9.594034744}]},{"c":[{"v":"21"},{"v":9.903447816}]},{"c":[{"v":"21"},{"v":9.545568792}]},{"c":[{"v":"21"},{"v":9.705717888}]},{"c":[{"v":"21"},{"v":9.29396872}]},{"c":[{"v":"21"},{"v":9.3411532}]},{"c":[{"v":"22"},{"v":9.146800528}]},{"c":[{"v":"22"},{"v":9.439318424}]},{"c":[{"v":"22"},{"v":9.158496224}]},{"c":[{"v":"22"},{"v":9.173604744}]},{"c":[{"v":"22"},{"v":9.245244304}]},{"c":[{"v":"22"},{"v":9.112737384}]},{"c":[{"v":"22"},{"v":8.79768168}]},{"c":[{"v":"22"},{"v":8.86630804}]},{"c":[{"v":"22"},{"v":8.368063448}]},{"c":[{"v":"22"},{"v":8.029426328}]},{"c":[{"v":"22"},{"v":7.943864536}]},{"c":[{"v":"22"},{"v":7.840786208}]},{"c":[{"v":"23"},{"v":7.806853368}]},{"c":[{"v":"23"},{"v":7.654723184}]},{"c":[{"v":"23"},{"v":7.610355536}]},{"c":[{"v":"23"},{"v":7.440746224}]},{"c":[{"v":"23"},{"v":7.146271144}]},{"c":[{"v":"23"},{"v":7.110154176}]},{"c":[{"v":"23"},{"v":7.070385288}]},{"c":[{"v":"23"},{"v":6.98368116}]},{"c":[{"v":"23"},{"v":6.651502944}]},{"c":[{"v":"23"},{"v":6.503646608}]},{"c":[{"v":"23"},{"v":6.3847106}]},{"c":[{"v":"23"},{"v":6.15990412}]},{"c":[{"v":"00"},{"v":6.171424744}]},{"c":[{"v":"00"},{"v":6.209126488}]},{"c":[{"v":"00"},{"v":6.145579736}]},{"c":[{"v":"00"},{"v":5.934775416}]},{"c":[{"v":"00"},{"v":5.815688384}]},{"c":[{"v":"00"},{"v":5.74235052}]},{"c":[{"v":"00"},{"v":5.621224656}]},{"c":[{"v":"00"},{"v":5.548128936}]},{"c":[{"v":"00"},{"v":5.325556848}]},{"c":[{"v":"00"},{"v":5.33839556}]},{"c":[{"v":"00"},{"v":5.296974168}]},{"c":[{"v":"00"},{"v":5.057273032}]},{"c":[{"v":"01"},{"v":4.921321128}]},{"c":[{"v":"01"},{"v":4.877572648}]},{"c":[{"v":"01"},{"v":4.7708142}]},{"c":[{"v":"01"},{"v":4.799478016}]},{"c":[{"v":"01"},{"v":4.741192944}]},{"c":[{"v":"01"},{"v":4.737051176}]},{"c":[{"v":"01"},{"v":4.577258256}]},{"c":[{"v":"01"},{"v":4.484735384}]},{"c":[{"v":"01"},{"v":4.453364408}]},{"c":[{"v":"01"},{"v":4.286329488}]},{"c":[{"v":"01"},{"v":4.261492112}]},{"c":[{"v":"01"},{"v":4.234042376}]},{"c":[{"v":"02"},{"v":4.242016936}]},{"c":[{"v":"02"},{"v":4.25954884}]},{"c":[{"v":"02"},{"v":4.132705096}]},{"c":[{"v":"02"},{"v":4.132551392}]},{"c":[{"v":"02"},{"v":4.2144176}]},{"c":[{"v":"02"},{"v":4.065578992}]},{"c":[{"v":"02"},{"v":4.086175744}]},{"c":[{"v":"02"},{"v":4.129475672}]},{"c":[{"v":"02"},{"v":4.041719864}]},{"c":[{"v":"02"},{"v":4.014502968}]},{"c":[{"v":"02"},{"v":3.9397746}]},{"c":[{"v":"02"},{"v":3.891914248}]},{"c":[{"v":"03"},{"v":3.893345984}]},{"c":[{"v":"03"},{"v":4.063784192}]},{"c":[{"v":"03"},{"v":3.901075472}]},{"c":[{"v":"03"},{"v":3.900802792}]},{"c":[{"v":"03"},{"v":3.886163616}]},{"c":[{"v":"03"},{"v":3.767963832}]},{"c":[{"v":"03"},{"v":3.85939716}]},{"c":[{"v":"03"},{"v":3.878149656}]},{"c":[{"v":"03"},{"v":3.844933584}]},{"c":[{"v":"03"},{"v":3.88251396}]},{"c":[{"v":"03"},{"v":3.84913748}]},{"c":[{"v":"03"},{"v":3.809615928}]},{"c":[{"v":"04"},{"v":3.846610816}]},{"c":[{"v":"04"},{"v":3.860192392}]},{"c":[{"v":"04"},{"v":3.852115}]},{"c":[{"v":"04"},{"v":3.780852872}]},{"c":[{"v":"04"},{"v":3.692258456}]},{"c":[{"v":"04"},{"v":3.692970424}]},{"c":[{"v":"04"},{"v":3.71231148}]},{"c":[{"v":"04"},{"v":3.79049292}]},{"c":[{"v":"04"},{"v":3.70679636}]},{"c":[{"v":"04"},{"v":3.700532168}]},{"c":[{"v":"04"},{"v":3.724480872}]},{"c":[{"v":"04"},{"v":3.685471552}]},{"c":[{"v":"05"},{"v":3.731707224}]},{"c":[{"v":"05"},{"v":3.8107362}]},{"c":[{"v":"05"},{"v":3.771226696}]},{"c":[{"v":"05"},{"v":3.894805368}]},{"c":[{"v":"05"},{"v":3.913976576}]},{"c":[{"v":"05"},{"v":3.886462648}]},{"c":[{"v":"05"},{"v":3.831131536}]},{"c":[{"v":"05"},{"v":3.893367792}]},{"c":[{"v":"05"},{"v":3.944959424}]},{"c":[{"v":"05"},{"v":3.901093048}]},{"c":[{"v":"05"},{"v":3.890752072}]},{"c":[{"v":"05"},{"v":3.919476904}]},{"c":[{"v":"06"},{"v":4.034067528}]},{"c":[{"v":"06"},{"v":4.197740016}]},{"c":[{"v":"06"},{"v":4.390481592}]},{"c":[{"v":"06"},{"v":4.408604096}]},{"c":[{"v":"06"},{"v":4.369811888}]},{"c":[{"v":"06"},{"v":4.473580784}]},{"c":[{"v":"06"},{"v":4.506093088}]},{"c":[{"v":"06"},{"v":4.46887564}]},{"c":[{"v":"06"},{"v":4.554222544}]},{"c":[{"v":"06"},{"v":4.69296864}]},{"c":[{"v":"06"},{"v":4.761283}]},{"c":[{"v":"06"},{"v":4.737793928}]},{"c":[{"v":"07"},{"v":4.873513832}]},{"c":[{"v":"07"},{"v":5.004962688}]},{"c":[{"v":"07"},{"v":5.100404664}]},{"c":[{"v":"07"},{"v":5.066162536}]},{"c":[{"v":"07"},{"v":5.636175856}]},{"c":[{"v":"07"},{"v":5.878934888}]},{"c":[{"v":"07"},{"v":5.329191216}]},{"c":[{"v":"07"},{"v":5.436100112}]},{"c":[{"v":"07"},{"v":5.537473296}]},{"c":[{"v":"07"},{"v":5.706589016}]},{"c":[{"v":"07"},{"v":5.719357144}]},{"c":[{"v":"07"},{"v":5.734095792}]},{"c":[{"v":"08"},{"v":5.800705856}]},{"c":[{"v":"08"},{"v":5.869391}]},{"c":[{"v":"08"},{"v":5.967101672}]},{"c":[{"v":"08"},{"v":6.207961824}]},{"c":[{"v":"08"},{"v":6.465453088}]},{"c":[{"v":"08"},{"v":6.508792952}]},{"c":[{"v":"08"},{"v":6.612667136}]},{"c":[{"v":"08"},{"v":6.59797188}]},{"c":[{"v":"08"},{"v":6.538816888}]},{"c":[{"v":"08"},{"v":6.537696752}]},{"c":[{"v":"08"},{"v":6.461688232}]},{"c":[{"v":"08"},{"v":6.573611096}]},{"c":[{"v":"09"},{"v":6.723590744}]},{"c":[{"v":"09"},{"v":6.718727464}]},{"c":[{"v":"09"},{"v":6.724163376}]},{"c":[{"v":"09"},{"v":6.90662016}]},{"c":[{"v":"09"},{"v":7.047425696}]},{"c":[{"v":"09"},{"v":7.182292848}]},{"c":[{"v":"09"},{"v":7.008459784}]},{"c":[{"v":"09"},{"v":7.21410776}]},{"c":[{"v":"09"},{"v":6.99615672}]},{"c":[{"v":"09"},{"v":7.037630304}]},{"c":[{"v":"09"},{"v":7.005563488}]},{"c":[{"v":"09"},{"v":6.962918408}]},{"c":[{"v":"10"},{"v":7.107233072}]},{"c":[{"v":"10"},{"v":7.658392912}]},{"c":[{"v":"10"},{"v":7.601708328}]},{"c":[{"v":"10"},{"v":7.790230344}]},{"c":[{"v":"10"},{"v":7.685917296}]},{"c":[{"v":"10"},{"v":7.267143248}]},{"c":[{"v":"10"},{"v":7.38900516}]},{"c":[{"v":"10"},{"v":7.236769448}]},{"c":[{"v":"10"},{"v":7.176860632}]},{"c":[{"v":"10"},{"v":7.188440768}]},{"c":[{"v":"10"},{"v":7.403804504}]},{"c":[{"v":"10"},{"v":7.464587112}]},{"c":[{"v":"11"},{"v":7.470329656}]},{"c":[{"v":"11"},{"v":7.417122672}]},{"c":[{"v":"11"},{"v":7.344187488}]},{"c":[{"v":"11"},{"v":7.28169364}]},{"c":[{"v":"11"},{"v":7.526051304}]},{"c":[{"v":"11"},{"v":7.302914856}]},{"c":[{"v":"11"},{"v":7.216675368}]},{"c":[{"v":"11"},{"v":7.312817144}]},{"c":[{"v":"11"},{"v":7.175406784}]},{"c":[{"v":"11"},{"v":7.275012144}]},{"c":[{"v":"11"},{"v":7.31721832}]},{"c":[{"v":"11"},{"v":7.375473424}]},{"c":[{"v":"12"},{"v":7.114721416}]},{"c":[{"v":"12"},{"v":7.263759088}]},{"c":[{"v":"12"},{"v":7.39177292}]},{"c":[{"v":"12"},{"v":7.301379192}]},{"c":[{"v":"12"},{"v":7.416445784}]},{"c":[{"v":"12"},{"v":7.48745172}]},{"c":[{"v":"12"},{"v":7.700360592}]},{"c":[{"v":"12"},{"v":7.599001504}]},{"c":[{"v":"12"},{"v":7.586606936}]},{"c":[{"v":"12"},{"v":7.513304352}]},{"c":[{"v":"12"},{"v":7.633827832}]},{"c":[{"v":"12"},{"v":7.542383632}]},{"c":[{"v":"12"},{"v":7.541761728}]},{"c":[{"v":"13"},{"v":7.668697672}]}]}