{"cols":[{"type":"string"},{"type":"number"}],"rows":[{"c":[{"v":"03"},{"v":103.095477016}]},{"c":[{"v":"03"},{"v":100.3075548}]},{"c":[{"v":"03"},{"v":97.035290896}]},{"c":[{"v":"03"},{"v":96.056107024}]},{"c":[{"v":"03"},{"v":94.208800048}]},{"c":[{"v":"03"},{"v":90.51743916}]},{"c":[{"v":"03"},{"v":90.93505748}]},{"c":[{"v":"03"},{"v":88.818144224}]},{"c":[{"v":"03"},{"v":86.806838008}]},{"c":[{"v":"03"},{"v":85.677985152}]},{"c":[{"v":"03"},{"v":85.093463848}]},{"c":[{"v":"04"},{"v":83.193559928}]},{"c":[{"v":"04"},{"v":86.101894544}]},{"c":[{"v":"04"},{"v":83.406630272}]},{"c":[{"v":"04"},{"v":81.514366424}]},{"c":[{"v":"04"},{"v":82.660189312}]},{"c":[{"v":"04"},{"v":81.66405576}]},{"c":[{"v":"04"},{"v":80.067415776}]},{"c":[{"v":"04"},{"v":81.848372104}]},{"c":[{"v":"04"},{"v":81.691446552}]},{"c":[{"v":"04"},{"v":81.457082976}]},{"c":[{"v":"04"},{"v":79.893709952}]},{"c":[{"v":"04"},{"v":79.01288232}]},{"c":[{"v":"05"},{"v":79.42725652}]},{"c":[{"v":"05"},{"v":82.09332696}]},{"c":[{"v":"05"},{"v":80.446406208}]},{"c":[{"v":"05"},{"v":78.734178592}]},{"c":[{"v":"05"},{"v":80.372455216}]},{"c":[{"v":"05"},{"v":79.299327256}]},{"c":[{"v":"05"},{"v":79.22548788}]},{"c":[{"v":"05"},{"v":81.6368896}]},{"c":[{"v":"05"},{"v":81.154212776}]},{"c":[{"v":"05"},{"v":81.044553272}]},{"c":[{"v":"05"},{"v":83.42520068}]},{"c":[{"v":"05"},{"v":84.633582184}]},{"c":[{"v":"06"},{"v":86.527011192}]},{"c":[{"v":"06"},{"v":89.95355124}]},{"c":[{"v":"06"},{"v":91.31554988}]},{"c":[{"v":"06"},{"v":90.831698856}]},{"c":[{"v":"06"},{"v":94.330796032}]},{"c":[{"v":"06"},{"v":95.066002824}]},{"c":[{"v":"06"},{"v":99.871243064}]},{"c":[{"v":"06"},{"v":103.506240488}]},{"c":[{"v":"06"},{"v":107.063047064}]},{"c":[{"v":"06"},{"v":111.301249768}]},{"c":[{"v":"06"},{"v":117.522876096}]},{"c":[{"v":"06"},{"v":120.8104088}]},{"c":[{"v":"07"},{"v":128.143039816}]},{"c":[{"v":"07"},{"v":135.010787568}]},{"c":[{"v":"07"},{"v":139.644257256}]},{"c":[{"v":"07"},{"v":144.607752744}]},{"c":[{"v":"07"},{"v":153.769819832}]},{"c":[{"v":"07"},{"v":159.034467304}]},{"c":[{"v":"07"},{"v":165.290200216}]},{"c":[{"v":"07"},{"v":169.534412968}]},{"c":[{"v":"07"},{"v":177.835121328}]},{"c":[{"v":"07"},{"v":182.048772752}]},{"c":[{"v":"07"},{"v":191.248724176}]},{"c":[{"v":"07"},{"v":193.076067832}]},{"c":[{"v":"08"},{"v":201.080524744}]},{"c":[{"v":"08"},{"v":209.692940208}]},{"c":[{"v":"08"},{"v":216.57066764}]},{"c":[{"v":"08"},{"v":219.479112344}]},{"c":[{"v":"08"},{"v":224.757314728}]},{"c":[{"v":"08"},{"v":227.865432008}]},{"c":[{"v":"08"},{"v":232.462105896}]},{"c":[{"v":"08"},{"v":234.658552536}]},{"c":[{"v":"08"},{"v":241.507928048}]},{"c":[{"v":"08"},{"v":242.545258992}]},{"c":[{"v":"08"},{"v":247.709112176}]},{"c":[{"v":"08"},{"v":253.04840368}]},{"c":[{"v":"09"},{"v":258.89872788}]},{"c":[{"v":"09"},{"v":259.905546808}]},{"c":[{"v":"09"},{"v":262.757823512}]},{"c":[{"v":"09"},{"v":267.166955768}]},{"c":[{"v":"09"},{"v":270.572628432}]},{"c":[{"v":"09"},{"v":272.618489216}]},{"c":[{"v":"09"},{"v":275.563748632}]},{"c":[{"v":"09"},{"v":278.222662128}]},{"c":[{"v":"09"},{"v":280.237720768}]},{"c":[{"v":"09"},{"v":287.315750912}]},{"c":[{"v":"09"},{"v":291.484086}]},{"c":[{"v":"09"},{"v":291.629337416}]},{"c":[{"v":"10"},{"v":294.610574904}]},{"c":[{"v":"10"},{"v":297.370375384}]},{"c":[{"v":"10"},{"v":299.921364544}]},{"c":[{"v":"10"},{"v":301.176178984}]},{"c":[{"v":"10"},{"v":303.997260272}]},{"c":[{"v":"10"},{"v":304.064501816}]},{"c":[{"v":"10"},{"v":307.314277776}]},{"c":[{"v":"10"},{"v":306.270965344}]},{"c":[{"v":"10"},{"v":311.170959792}]},{"c":[{"v":"10"},{"v":311.119649968}]},{"c":[{"v":"10"},{"v":312.250169304}]},{"c":[{"v":"10"},{"v":317.28212964}]},{"c":[{"v":"11"},{"v":319.25059128}]},{"c":[{"v":"11"},{"v":329.385244528}]},{"c":[{"v":"11"},{"v":311.049590632}]},{"c":[{"v":"11"},{"v":314.815342168}]},{"c":[{"v":"11"},{"v":319.622488608}]},{"c":[{"v":"11"},{"v":321.74634848}]},{"c":[{"v":"11"},{"v":325.1033792}]},{"c":[{"v":"11"},{"v":321.53383348}]},{"c":[{"v":"11"},{"v":322.481924016}]},{"c":[{"v":"11"},{"v":323.911194408}]},{"c":[{"v":"11"},{"v":324.437053224}]},{"c":[{"v":"11"},{"v":324.44996092}]},{"c":[{"v":"12"},{"v":326.56055716}]},{"c":[{"v":"12"},{"v":332.047419104}]},{"c":[{"v":"12"},{"v":318.688816408}]},{"c":[{"v":"12"},{"v":322.939840224}]},{"c":[{"v":"12"},{"v":325.265279472}]},{"c":[{"v":"12"},{"v":327.183973256}]},{"c":[{"v":"12"},{"v":330.98405168}]},{"c":[{"v":"12"},{"v":333.01664372}]},{"c":[{"v":"12"},{"v":332.217422464}]},{"c":[{"v":"12"},{"v":338.0069162}]},{"c":[{"v":"12"},{"v":337.736422232}]},{"c":[{"v":"12"},{"v":334.878965344}]},{"c":[{"v":"13"},{"v":338.434682128}]},{"c":[{"v":"13"},{"v":335.54477632}]},{"c":[{"v":"13"},{"v":332.85315708}]},{"c":[{"v":"13"},{"v":331.271310144}]},{"c":[{"v":"13"},{"v":336.41523704}]},{"c":[{"v":"13"},{"v":333.830446632}]},{"c":[{"v":"13"},{"v":331.2485448}]},{"c":[{"v":"13"},{"v":334.27154032}]},{"c":[{"v":"13"},{"v":335.673737648}]},{"c":[{"v":"13"},{"v":329.74354672}]},{"c":[{"v":"13"},{"v":328.89344008}]},{"c":[{"v":"13"},{"v":328.056763304}]},{"c":[{"v":"14"},{"v":326.929501632}]},{"c":[{"v":"14"},{"v":328.794781648}]},{"c":[{"v":"14"},{"v":323.425301176}]},{"c":[{"v":"14"},{"v":322.949904376}]},{"c":[{"v":"14"},{"v":326.568746168}]},{"c":[{"v":"14"},{"v":328.180891128}]},{"c":[{"v":"14"},{"v":326.099548392}]},{"c":[{"v":"14"},{"v":323.90953776}]},{"c":[{"v":"14"},{"v":323.127211464}]},{"c":[{"v":"14"},{"v":323.898313256}]},{"c":[{"v":"14"},{"v":323.399304592}]},{"c":[{"v":"14"},{"v":322.954798296}]},{"c":[{"v":"15"},{"v":324.232739176}]},{"c":[{"v":"15"},{"v":324.450100712}]},{"c":[{"v":"15"},{"v":327.82931868}]},{"c":[{"v":"15"},{"v":326.868819096}]},{"c":[{"v":"15"},{"v":329.42457588}]},{"c":[{"v":"15"},{"v":328.193376872}]},{"c":[{"v":"15"},{"v":328.16844752}]},{"c":[{"v":"15"},{"v":330.02099556}]},{"c":[{"v":"15"},{"v":329.055254344}]},{"c":[{"v":"15"},{"v":331.221480112}]},{"c":[{"v":"15"},{"v":337.108391304}]},{"c":[{"v":"15"},{"v":336.823891832}]},{"c":[{"v":"16"},{"v":339.879831808}]},{"c":[{"v":"16"},{"v":338.174366792}]},{"c":[{"v":"16"},{"v":340.714670904}]},{"c":[{"v":"16"},{"v":341.745842488}]},{"c":[{"v":"16"},{"v":345.254127664}]},{"c":[{"v":"16"},{"v":347.474331816}]},{"c":[{"v":"16"},{"v":348.887206448}]},{"c":[{"v":"16"},{"v":347.745461064}]},{"c":[{"v":"16"},{"v":353.789048464}]},{"c":[{"v":"16"},{"v":355.233558424}]},{"c":[{"v":"16"},{"v":361.187686392}]},{"c":[{"v":"16"},{"v":358.790899696}]},{"c":[{"v":"17"},{"v":362.48003976}]},{"c":[{"v":"17"},{"v":363.574925824}]},{"c":[{"v":"17"},{"v":367.007318744}]},{"c":[{"v":"17"},{"v":370.201692576}]},{"c":[{"v":"17"},{"v":372.764936184}]},{"c":[{"v":"17"},{"v":376.966412904}]},{"c":[{"v":"17"},{"v":376.01696656}]},{"c":[{"v":"17"},{"v":376.669036216}]},{"c":[{"v":"17"},{"v":382.748715176}]},{"c":[{"v":"17"},{"v":377.566719808}]},{"c":[{"v":"17"},{"v":384.068659368}]},{"c":[{"v":"17"},{"v":377.374512704}]},{"c":[{"v":"18"},{"v":386.153156472}]},{"c":[{"v":"18"},{"v":384.172860504}]},{"c":[{"v":"18"},{"v":389.244005032}]},{"c":[{"v":"18"},{"v":389.344886776}]},{"c":[{"v":"18"},{"v":392.662231032}]},{"c":[{"v":"18"},{"v":393.670508912}]},{"c":[{"v":"18"},{"v":394.461947016}]},{"c":[{"v":"18"},{"v":399.977777616}]},{"c":[{"v":"18"},{"v":399.542294416}]},{"c":[{"v":"18"},{"v":394.019453624}]},{"c":[{"v":"18"},{"v":398.641342456}]},{"c":[{"v":"18"},{"v":393.56824444}]},{"c":[{"v":"19"},{"v":394.121153768}]},{"c":[{"v":"19"},{"v":393.640246576}]},{"c":[{"v":"19"},{"v":398.806486312}]},{"c":[{"v":"19"},{"v":396.41999008}]},{"c":[{"v":"19"},{"v":402.09448784}]},{"c":[{"v":"19"},{"v":397.968221216}]},{"c":[{"v":"19"},{"v":404.052980744}]},{"c":[{"v":"19"},{"v":400.131348192}]},{"c":[{"v":"19"},{"v":404.790448976}]},{"c":[{"v":"19"},{"v":398.583358936}]},{"c":[{"v":"19"},{"v":405.931533656}]},{"c":[{"v":"19"},{"v":403.942432296}]},{"c":[{"v":"20"},{"v":397.440614448}]},{"c":[{"v":"20"},{"v":403.219936224}]},{"c":[{"v":"20"},{"v":402.400600424}]},{"c":[{"v":"20"},{"v":402.3994508}]},{"c":[{"v":"20"},{"v":405.297318968}]},{"c":[{"v":"20"},{"v":402.391069896}]},{"c":[{"v":"20"},{"v":400.938721128}]},{"c":[{"v":"20"},{"v":396.125741752}]},{"c":[{"v":"20"},{"v":397.9014264}]},{"c":[{"v":"20"},{"v":394.102864296}]},{"c":[{"v":"20"},{"v":394.319420512}]},{"c":[{"v":"20"},{"v":391.420506792}]},{"c":[{"v":"21"},{"v":394.886060992}]},{"c":[{"v":"21"},{"v":390.304045952}]},{"c":[{"v":"21"},{"v":388.147882928}]},{"c":[{"v":"21"},{"v":389.615273024}]},{"c":[{"v":"21"},{"v":388.123604944}]},{"c":[{"v":"21"},{"v":382.593325888}]},{"c":[{"v":"21"},{"v":381.644221208}]},{"c":[{"v":"21"},{"v":380.944801288}]},{"c":[{"v":"21"},{"v":375.215715568}]},{"c":[{"v":"21"},{"v":373.448169672}]},{"c":[{"v":"21"},{"v":372.01938828}]},{"c":[{"v":"21"},{"v":365.040362224}]},{"c":[{"v":"22"},{"v":361.716246576}]},{"c":[{"v":"22"},{"v":362.479411104}]},{"c":[{"v":"22"},{"v":359.199072808}]},{"c":[{"v":"22"},{"v":355.808607728}]},{"c":[{"v":"22"},{"v":350.665850032}]},{"c":[{"v":"22"},{"v":344.053636048}]},{"c":[{"v":"22"},{"v":335.039613528}]},{"c":[{"v":"22"},{"v":333.860314392}]},{"c":[{"v":"22"},{"v":329.661158144}]},{"c":[{"v":"22"},{"v":325.033593048}]},{"c":[{"v":"22"},{"v":318.796741416}]},{"c":[{"v":"22"},{"v":311.205945784}]},{"c":[{"v":"23"},{"v":303.800949712}]},{"c":[{"v":"23"},{"v":299.978516104}]},{"c":[{"v":"23"},{"v":299.039769656}]},{"c":[{"v":"23"},{"v":296.330285304}]},{"c":[{"v":"23"},{"v":285.876442224}]},{"c":[{"v":"23"},{"v":279.876229584}]},{"c":[{"v":"23"},{"v":274.073987104}]},{"c":[{"v":"23"},{"v":268.551312072}]},{"c":[{"v":"23"},{"v":261.532364656}]},{"c":[{"v":"23"},{"v":252.958737048}]},{"c":[{"v":"23"},{"v":245.69276252}]},{"c":[{"v":"23"},{"v":237.779013816}]},{"c":[{"v":"00"},{"v":230.91840596}]},{"c":[{"v":"00"},{"v":231.13868364}]},{"c":[{"v":"00"},{"v":227.472273928}]},{"c":[{"v":"00"},{"v":220.505318448}]},{"c":[{"v":"00"},{"v":213.176229696}]},{"c":[{"v":"00"},{"v":208.458096952}]},{"c":[{"v":"00"},{"v":200.526340272}]},{"c":[{"v":"00"},{"v":195.04232012}]},{"c":[{"v":"00"},{"v":187.357727936}]},{"c":[{"v":"00"},{"v":186.24463704}]},{"c":[{"v":"00"},{"v":177.103653912}]},{"c":[{"v":"00"},{"v":174.59664908}]},{"c":[{"v":"01"},{"v":170.235353936}]},{"c":[{"v":"01"},{"v":168.383800864}]},{"c":[{"v":"01"},{"v":164.432926448}]},{"c":[{"v":"01"},{"v":157.92258232}]},{"c":[{"v":"01"},{"v":156.365332312}]},{"c":[{"v":"01"},{"v":148.548824112}]},{"c":[{"v":"01"},{"v":147.48552276}]},{"c":[{"v":"01"},{"v":143.19874124}]},{"c":[{"v":"01"},{"v":139.869080976}]},{"c":[{"v":"01"},{"v":136.600056136}]},{"c":[{"v":"01"},{"v":133.722783648}]},{"c":[{"v":"01"},{"v":129.977804528}]},{"c":[{"v":"02"},{"v":127.45358924}]},{"c":[{"v":"02"},{"v":124.980199792}]},{"c":[{"v":"02"},{"v":123.324021192}]},{"c":[{"v":"02"},{"v":122.262978808}]},{"c":[{"v":"02"},{"v":119.977268888}]},{"c":[{"v":"02"},{"v":114.887814304}]},{"c":[{"v":"02"},{"v":113.690968472}]},{"c":[{"v":"02"},{"v":110.630897024}]},{"c":[{"v":"02"},{"v":107.978629984}]},{"c":[{"v":"02"},{"v":105.245230944}]},{"c":[{"v":"02"},{"v":103.917163032}]},{"c":[{"v":"02"},{"v":99.62487556}]},{"c":[{"v":"03"},{"v":98.590416928}]},{"c":[{"v":"03"},{"v":104.059803872}]},{"c":[{"v":"03"},{"v":99.272894432}]},{"c":[{"v":"03"},{"v":97.517713608}]},{"c":[{"v":"03"},{"v":96.183790296}]},{"c":[{"v":"03"},{"v":94.515966144}]},{"c":[{"v":"03"},{"v":91.223799904}]},{"c":[{"v":"03"},{"v":92.017066976}]},{"c":[{"v":"03"},{"v":89.83055416}]},{"c":[{"v":"03"},{"v":87.951562152}]},{"c":[{"v":"03"},{"v":86.28812804}]},{"c":[{"v":"03"},{"v":85.186303464}]},{"c":[{"v":"04"},{"v":83.121974312}]},{"c":[{"v":"04"},{"v":84.923907}]},{"c":[{"v":"04"},{"v":82.462628072}]},{"c":[{"v":"04"},{"v":81.9414086}]},{"c":[{"v":"04"},{"v":80.368825784}]},{"c":[{"v":"04"},{"v":79.75403836}]},{"c":[{"v":"04"},{"v":77.955846456}]},{"c":[{"v":"04"},{"v":78.209161296}]},{"c":[{"v":"04"},{"v":77.537423616}]},{"c":[{"v":"04"},{"v":76.8446442}]},{"c":[{"v":"04"},{"v":76.371422672}]},{"c":[{"v":"04"},{"v":74.249672896}]},{"c":[{"v":"04"},{"v":74.235496848}]},{"c":[{"v":"05"},{"v":74.87557068}]}]}