{"cols":[{"type":"string"},{"type":"number"}],"rows":[{"c":[{"v":"03"},{"v":10.301004864}]},{"c":[{"v":"03"},{"v":10.039268216}]},{"c":[{"v":"03"},{"v":9.691506392}]},{"c":[{"v":"03"},{"v":9.3823614}]},{"c":[{"v":"03"},{"v":9.307511272}]},{"c":[{"v":"03"},{"v":9.287949104}]},{"c":[{"v":"03"},{"v":9.24633472}]},{"c":[{"v":"03"},{"v":9.08560788}]},{"c":[{"v":"03"},{"v":8.94386452}]},{"c":[{"v":"03"},{"v":9.061301488}]},{"c":[{"v":"03"},{"v":8.732139672}]},{"c":[{"v":"04"},{"v":8.395415824}]},{"c":[{"v":"04"},{"v":8.979058528}]},{"c":[{"v":"04"},{"v":8.551136608}]},{"c":[{"v":"04"},{"v":8.422588384}]},{"c":[{"v":"04"},{"v":8.487524208}]},{"c":[{"v":"04"},{"v":8.079674216}]},{"c":[{"v":"04"},{"v":8.260659184}]},{"c":[{"v":"04"},{"v":8.080432104}]},{"c":[{"v":"04"},{"v":8.236567312}]},{"c":[{"v":"04"},{"v":7.847022256}]},{"c":[{"v":"04"},{"v":7.931120152}]},{"c":[{"v":"04"},{"v":7.757339224}]},{"c":[{"v":"05"},{"v":7.737875688}]},{"c":[{"v":"05"},{"v":7.75409316}]},{"c":[{"v":"05"},{"v":7.933391512}]},{"c":[{"v":"05"},{"v":8.066282712}]},{"c":[{"v":"05"},{"v":8.1139262}]},{"c":[{"v":"05"},{"v":8.121393304}]},{"c":[{"v":"05"},{"v":8.15151128}]},{"c":[{"v":"05"},{"v":8.268565512}]},{"c":[{"v":"05"},{"v":8.250679496}]},{"c":[{"v":"05"},{"v":8.303379528}]},{"c":[{"v":"05"},{"v":8.390906568}]},{"c":[{"v":"05"},{"v":8.483328272}]},{"c":[{"v":"06"},{"v":8.779450592}]},{"c":[{"v":"06"},{"v":9.54407548}]},{"c":[{"v":"06"},{"v":9.433668328}]},{"c":[{"v":"06"},{"v":9.630582768}]},{"c":[{"v":"06"},{"v":9.525765}]},{"c":[{"v":"06"},{"v":10.063476472}]},{"c":[{"v":"06"},{"v":9.803718752}]},{"c":[{"v":"06"},{"v":10.019011304}]},{"c":[{"v":"06"},{"v":10.202765984}]},{"c":[{"v":"06"},{"v":10.63637072}]},{"c":[{"v":"06"},{"v":10.98899888}]},{"c":[{"v":"06"},{"v":11.188761048}]},{"c":[{"v":"07"},{"v":11.890358288}]},{"c":[{"v":"07"},{"v":12.207794304}]},{"c":[{"v":"07"},{"v":13.187629072}]},{"c":[{"v":"07"},{"v":13.486377464}]},{"c":[{"v":"07"},{"v":13.1827672}]},{"c":[{"v":"07"},{"v":13.821750296}]},{"c":[{"v":"07"},{"v":14.299849072}]},{"c":[{"v":"07"},{"v":15.362189376}]},{"c":[{"v":"07"},{"v":15.794717464}]},{"c":[{"v":"07"},{"v":16.301759864}]},{"c":[{"v":"07"},{"v":16.693577864}]},{"c":[{"v":"07"},{"v":17.028302864}]},{"c":[{"v":"08"},{"v":17.395969824}]},{"c":[{"v":"08"},{"v":18.523105776}]},{"c":[{"v":"08"},{"v":18.5401914}]},{"c":[{"v":"08"},{"v":19.59515836}]},{"c":[{"v":"08"},{"v":20.173881192}]},{"c":[{"v":"08"},{"v":20.61232936}]},{"c":[{"v":"08"},{"v":21.350433872}]},{"c":[{"v":"08"},{"v":21.327804096}]},{"c":[{"v":"08"},{"v":21.73599212}]},{"c":[{"v":"08"},{"v":21.727633752}]},{"c":[{"v":"08"},{"v":23.020679408}]},{"c":[{"v":"08"},{"v":23.531044448}]},{"c":[{"v":"09"},{"v":24.039537608}]},{"c":[{"v":"09"},{"v":24.963325576}]},{"c":[{"v":"09"},{"v":24.487801272}]},{"c":[{"v":"09"},{"v":25.810737184}]},{"c":[{"v":"09"},{"v":25.986244632}]},{"c":[{"v":"09"},{"v":26.294997104}]},{"c":[{"v":"09"},{"v":26.276466136}]},{"c":[{"v":"09"},{"v":27.334926888}]},{"c":[{"v":"09"},{"v":26.844244104}]},{"c":[{"v":"09"},{"v":26.73264704}]},{"c":[{"v":"09"},{"v":27.050380216}]},{"c":[{"v":"09"},{"v":27.131548792}]},{"c":[{"v":"10"},{"v":27.726283112}]},{"c":[{"v":"10"},{"v":28.177909768}]},{"c":[{"v":"10"},{"v":28.440717336}]},{"c":[{"v":"10"},{"v":28.703043296}]},{"c":[{"v":"10"},{"v":28.503283936}]},{"c":[{"v":"10"},{"v":29.35708052}]},{"c":[{"v":"10"},{"v":30.07684152}]},{"c":[{"v":"10"},{"v":30.480907424}]},{"c":[{"v":"10"},{"v":30.68684912}]},{"c":[{"v":"10"},{"v":30.803731416}]},{"c":[{"v":"10"},{"v":30.96323048}]},{"c":[{"v":"10"},{"v":31.009717712}]},{"c":[{"v":"11"},{"v":31.240520552}]},{"c":[{"v":"11"},{"v":33.629902512}]},{"c":[{"v":"11"},{"v":31.54756628}]},{"c":[{"v":"11"},{"v":31.077636904}]},{"c":[{"v":"11"},{"v":31.279553888}]},{"c":[{"v":"11"},{"v":31.79960828}]},{"c":[{"v":"11"},{"v":32.149769504}]},{"c":[{"v":"11"},{"v":32.052695816}]},{"c":[{"v":"11"},{"v":31.882127136}]},{"c":[{"v":"11"},{"v":31.417774072}]},{"c":[{"v":"11"},{"v":33.0590044}]},{"c":[{"v":"11"},{"v":32.835357312}]},{"c":[{"v":"12"},{"v":32.563787416}]},{"c":[{"v":"12"},{"v":34.393885432}]},{"c":[{"v":"12"},{"v":32.115674408}]},{"c":[{"v":"12"},{"v":33.073584376}]},{"c":[{"v":"12"},{"v":33.802600376}]},{"c":[{"v":"12"},{"v":33.904111336}]},{"c":[{"v":"12"},{"v":33.787228736}]},{"c":[{"v":"12"},{"v":33.742243128}]},{"c":[{"v":"12"},{"v":33.487838032}]},{"c":[{"v":"12"},{"v":33.770750944}]},{"c":[{"v":"12"},{"v":34.431799408}]},{"c":[{"v":"12"},{"v":33.5439828}]},{"c":[{"v":"13"},{"v":34.305302912}]},{"c":[{"v":"13"},{"v":34.156252328}]},{"c":[{"v":"13"},{"v":34.715321704}]},{"c":[{"v":"13"},{"v":34.663095512}]},{"c":[{"v":"13"},{"v":34.232721}]},{"c":[{"v":"13"},{"v":35.3593108}]},{"c":[{"v":"13"},{"v":34.603630248}]},{"c":[{"v":"13"},{"v":34.887642192}]},{"c":[{"v":"13"},{"v":35.849260368}]},{"c":[{"v":"13"},{"v":35.047015928}]},{"c":[{"v":"13"},{"v":35.571247072}]},{"c":[{"v":"13"},{"v":36.58874016}]},{"c":[{"v":"14"},{"v":34.893205808}]},{"c":[{"v":"14"},{"v":35.633718352}]},{"c":[{"v":"14"},{"v":34.67962056}]},{"c":[{"v":"14"},{"v":35.516375672}]},{"c":[{"v":"14"},{"v":35.521930528}]},{"c":[{"v":"14"},{"v":35.664287624}]},{"c":[{"v":"14"},{"v":36.082789032}]},{"c":[{"v":"14"},{"v":35.704425208}]},{"c":[{"v":"14"},{"v":35.815357016}]},{"c":[{"v":"14"},{"v":36.163272752}]},{"c":[{"v":"14"},{"v":35.642712272}]},{"c":[{"v":"14"},{"v":35.639202944}]},{"c":[{"v":"15"},{"v":35.639202944}]},{"c":[{"v":"15"},{"v":35.639202944}]},{"c":[{"v":"15"},{"v":35.596979328}]},{"c":[{"v":"15"},{"v":35.885637696}]},{"c":[{"v":"15"},{"v":35.183196344}]},{"c":[{"v":"15"},{"v":35.217326328}]},{"c":[{"v":"15"},{"v":35.229688656}]},{"c":[{"v":"15"},{"v":34.896901744}]},{"c":[{"v":"15"},{"v":34.8278786}]},{"c":[{"v":"15"},{"v":35.142936488}]},{"c":[{"v":"15"},{"v":34.90062112}]},{"c":[{"v":"15"},{"v":35.538448792}]},{"c":[{"v":"16"},{"v":35.344580584}]},{"c":[{"v":"16"},{"v":35.864167056}]},{"c":[{"v":"16"},{"v":36.856155536}]},{"c":[{"v":"16"},{"v":37.029716872}]},{"c":[{"v":"16"},{"v":36.995476016}]},{"c":[{"v":"16"},{"v":36.381676784}]},{"c":[{"v":"16"},{"v":36.367485736}]},{"c":[{"v":"16"},{"v":36.423963288}]},{"c":[{"v":"16"},{"v":37.500780256}]},{"c":[{"v":"16"},{"v":36.756414048}]},{"c":[{"v":"16"},{"v":37.727762976}]},{"c":[{"v":"16"},{"v":37.313826656}]},{"c":[{"v":"17"},{"v":36.358735048}]},{"c":[{"v":"17"},{"v":36.604181008}]},{"c":[{"v":"17"},{"v":37.02552776}]},{"c":[{"v":"17"},{"v":37.185261304}]},{"c":[{"v":"17"},{"v":36.880099648}]},{"c":[{"v":"17"},{"v":37.641723416}]},{"c":[{"v":"17"},{"v":37.351192544}]},{"c":[{"v":"17"},{"v":38.212278416}]},{"c":[{"v":"17"},{"v":38.03090496}]},{"c":[{"v":"17"},{"v":37.457503648}]},{"c":[{"v":"17"},{"v":38.085195832}]},{"c":[{"v":"17"},{"v":38.24604144}]},{"c":[{"v":"18"},{"v":38.415841808}]},{"c":[{"v":"18"},{"v":39.724353008}]},{"c":[{"v":"18"},{"v":39.20122532}]},{"c":[{"v":"18"},{"v":38.721185456}]},{"c":[{"v":"18"},{"v":39.00575448}]},{"c":[{"v":"18"},{"v":39.195865384}]},{"c":[{"v":"18"},{"v":39.059812656}]},{"c":[{"v":"18"},{"v":39.383963256}]},{"c":[{"v":"18"},{"v":38.9539162}]},{"c":[{"v":"18"},{"v":39.306832304}]},{"c":[{"v":"18"},{"v":39.710746032}]},{"c":[{"v":"18"},{"v":38.9904966}]},{"c":[{"v":"19"},{"v":39.033464168}]},{"c":[{"v":"19"},{"v":39.649294736}]},{"c":[{"v":"19"},{"v":40.619189416}]},{"c":[{"v":"19"},{"v":40.399871928}]},{"c":[{"v":"19"},{"v":39.824436504}]},{"c":[{"v":"19"},{"v":40.465143472}]},{"c":[{"v":"19"},{"v":40.111788296}]},{"c":[{"v":"19"},{"v":41.162407936}]},{"c":[{"v":"19"},{"v":40.43024764}]},{"c":[{"v":"19"},{"v":42.084832976}]},{"c":[{"v":"19"},{"v":41.285555504}]},{"c":[{"v":"19"},{"v":41.3850518}]},{"c":[{"v":"20"},{"v":41.421359184}]},{"c":[{"v":"20"},{"v":41.44446892}]},{"c":[{"v":"20"},{"v":42.206533824}]},{"c":[{"v":"20"},{"v":41.83178388}]},{"c":[{"v":"20"},{"v":41.87390912}]},{"c":[{"v":"20"},{"v":42.18917136}]},{"c":[{"v":"20"},{"v":42.280655784}]},{"c":[{"v":"20"},{"v":42.261356248}]},{"c":[{"v":"20"},{"v":42.130107712}]},{"c":[{"v":"20"},{"v":41.412822224}]},{"c":[{"v":"20"},{"v":40.604643352}]},{"c":[{"v":"20"},{"v":40.98697704}]},{"c":[{"v":"21"},{"v":40.063745464}]},{"c":[{"v":"21"},{"v":40.767512904}]},{"c":[{"v":"21"},{"v":40.402453912}]},{"c":[{"v":"21"},{"v":39.658533656}]},{"c":[{"v":"21"},{"v":39.138035856}]},{"c":[{"v":"21"},{"v":38.714253872}]},{"c":[{"v":"21"},{"v":39.797268808}]},{"c":[{"v":"21"},{"v":39.255894352}]},{"c":[{"v":"21"},{"v":39.765686528}]},{"c":[{"v":"21"},{"v":38.787336784}]},{"c":[{"v":"21"},{"v":38.479906416}]},{"c":[{"v":"21"},{"v":38.701886984}]},{"c":[{"v":"22"},{"v":38.445598552}]},{"c":[{"v":"22"},{"v":37.897805776}]},{"c":[{"v":"22"},{"v":36.39467032}]},{"c":[{"v":"22"},{"v":37.17743932}]},{"c":[{"v":"22"},{"v":36.585323928}]},{"c":[{"v":"22"},{"v":35.288163352}]},{"c":[{"v":"22"},{"v":35.636104832}]},{"c":[{"v":"22"},{"v":35.09291308}]},{"c":[{"v":"22"},{"v":35.021601256}]},{"c":[{"v":"22"},{"v":34.429934568}]},{"c":[{"v":"22"},{"v":33.956527608}]},{"c":[{"v":"22"},{"v":33.132819544}]},{"c":[{"v":"23"},{"v":32.89853136}]},{"c":[{"v":"23"},{"v":32.603179312}]},{"c":[{"v":"23"},{"v":31.582322936}]},{"c":[{"v":"23"},{"v":31.082453952}]},{"c":[{"v":"23"},{"v":30.044832248}]},{"c":[{"v":"23"},{"v":29.01246888}]},{"c":[{"v":"23"},{"v":29.211062944}]},{"c":[{"v":"23"},{"v":28.302852184}]},{"c":[{"v":"23"},{"v":28.020534328}]},{"c":[{"v":"23"},{"v":27.197447736}]},{"c":[{"v":"23"},{"v":26.154581096}]},{"c":[{"v":"23"},{"v":25.914590224}]},{"c":[{"v":"00"},{"v":25.408559208}]},{"c":[{"v":"00"},{"v":24.699008112}]},{"c":[{"v":"00"},{"v":23.575130288}]},{"c":[{"v":"00"},{"v":23.816044272}]},{"c":[{"v":"00"},{"v":22.906504416}]},{"c":[{"v":"00"},{"v":21.851131312}]},{"c":[{"v":"00"},{"v":21.818276384}]},{"c":[{"v":"00"},{"v":20.818701312}]},{"c":[{"v":"00"},{"v":20.8517722}]},{"c":[{"v":"00"},{"v":20.021377384}]},{"c":[{"v":"00"},{"v":19.941633512}]},{"c":[{"v":"00"},{"v":19.497038376}]},{"c":[{"v":"01"},{"v":18.568881544}]},{"c":[{"v":"01"},{"v":18.27659696}]},{"c":[{"v":"01"},{"v":17.097222424}]},{"c":[{"v":"01"},{"v":16.832092424}]},{"c":[{"v":"01"},{"v":16.587525752}]},{"c":[{"v":"01"},{"v":16.04035272}]},{"c":[{"v":"01"},{"v":16.155257072}]},{"c":[{"v":"01"},{"v":15.732782488}]},{"c":[{"v":"01"},{"v":14.799177064}]},{"c":[{"v":"01"},{"v":14.28577288}]},{"c":[{"v":"01"},{"v":14.492454984}]},{"c":[{"v":"01"},{"v":14.409986984}]},{"c":[{"v":"02"},{"v":13.917516528}]},{"c":[{"v":"02"},{"v":13.298351032}]},{"c":[{"v":"02"},{"v":12.58308024}]},{"c":[{"v":"02"},{"v":12.57356192}]},{"c":[{"v":"02"},{"v":12.326540224}]},{"c":[{"v":"02"},{"v":11.689393856}]},{"c":[{"v":"02"},{"v":11.64092928}]},{"c":[{"v":"02"},{"v":11.375036056}]},{"c":[{"v":"02"},{"v":11.4020092}]},{"c":[{"v":"02"},{"v":10.91521916}]},{"c":[{"v":"02"},{"v":10.827603768}]},{"c":[{"v":"02"},{"v":10.662812648}]},{"c":[{"v":"03"},{"v":10.467064512}]},{"c":[{"v":"03"},{"v":11.188975712}]},{"c":[{"v":"03"},{"v":10.544058712}]},{"c":[{"v":"03"},{"v":10.725910536}]},{"c":[{"v":"03"},{"v":9.98024076}]},{"c":[{"v":"03"},{"v":9.902798832}]},{"c":[{"v":"03"},{"v":9.679585456}]},{"c":[{"v":"03"},{"v":9.677438344}]},{"c":[{"v":"03"},{"v":9.275699384}]},{"c":[{"v":"03"},{"v":9.010079744}]},{"c":[{"v":"03"},{"v":9.1362818}]},{"c":[{"v":"03"},{"v":9.081639896}]},{"c":[{"v":"04"},{"v":9.358518392}]},{"c":[{"v":"04"},{"v":8.87394972}]},{"c":[{"v":"04"},{"v":8.429028856}]},{"c":[{"v":"04"},{"v":8.489122368}]},{"c":[{"v":"04"},{"v":8.385900424}]},{"c":[{"v":"04"},{"v":8.418173624}]},{"c":[{"v":"04"},{"v":8.500871448}]},{"c":[{"v":"04"},{"v":8.563811176}]},{"c":[{"v":"04"},{"v":8.712751784}]},{"c":[{"v":"04"},{"v":8.261068448}]},{"c":[{"v":"04"},{"v":8.203126712}]},{"c":[{"v":"04"},{"v":8.045909776}]},{"c":[{"v":"04"},{"v":8.044327176}]},{"c":[{"v":"05"},{"v":8.20950928}]}]}