{"cols":[{"type":"string"},{"type":"number"}],"rows":[{"c":[{"v":"15"},{"v":19.418702352}]},{"c":[{"v":"15"},{"v":18.967490992}]},{"c":[{"v":"15"},{"v":18.642862648}]},{"c":[{"v":"15"},{"v":18.783089536}]},{"c":[{"v":"15"},{"v":18.473899352}]},{"c":[{"v":"15"},{"v":18.816625104}]},{"c":[{"v":"15"},{"v":18.907656944}]},{"c":[{"v":"15"},{"v":17.997568016}]},{"c":[{"v":"15"},{"v":19.317339472}]},{"c":[{"v":"15"},{"v":19.299124096}]},{"c":[{"v":"15"},{"v":18.947752664}]},{"c":[{"v":"16"},{"v":19.304774328}]},{"c":[{"v":"16"},{"v":19.312118992}]},{"c":[{"v":"16"},{"v":19.491754096}]},{"c":[{"v":"16"},{"v":19.239229536}]},{"c":[{"v":"16"},{"v":19.19223736}]},{"c":[{"v":"16"},{"v":19.546291704}]},{"c":[{"v":"16"},{"v":19.93042148}]},{"c":[{"v":"16"},{"v":19.911799528}]},{"c":[{"v":"16"},{"v":20.141350808}]},{"c":[{"v":"16"},{"v":20.028967912}]},{"c":[{"v":"16"},{"v":19.294273232}]},{"c":[{"v":"16"},{"v":19.510429824}]},{"c":[{"v":"17"},{"v":19.801022608}]},{"c":[{"v":"17"},{"v":19.916837584}]},{"c":[{"v":"17"},{"v":20.773054472}]},{"c":[{"v":"17"},{"v":20.24072324}]},{"c":[{"v":"17"},{"v":20.928908808}]},{"c":[{"v":"17"},{"v":20.211163904}]},{"c":[{"v":"17"},{"v":20.506163504}]},{"c":[{"v":"17"},{"v":20.587708576}]},{"c":[{"v":"17"},{"v":20.078487224}]},{"c":[{"v":"17"},{"v":20.214244776}]},{"c":[{"v":"17"},{"v":20.03631932}]},{"c":[{"v":"17"},{"v":19.76218816}]},{"c":[{"v":"18"},{"v":20.15111996}]},{"c":[{"v":"18"},{"v":20.62971988}]},{"c":[{"v":"18"},{"v":20.681115376}]},{"c":[{"v":"18"},{"v":20.852622736}]},{"c":[{"v":"18"},{"v":26.574692864}]},{"c":[{"v":"18"},{"v":32.923865232}]},{"c":[{"v":"18"},{"v":21.799876376}]},{"c":[{"v":"18"},{"v":21.772288992}]},{"c":[{"v":"18"},{"v":21.770745832}]},{"c":[{"v":"18"},{"v":21.641192936}]},{"c":[{"v":"18"},{"v":21.815689704}]},{"c":[{"v":"18"},{"v":21.391087088}]},{"c":[{"v":"19"},{"v":21.83882844}]},{"c":[{"v":"19"},{"v":21.803275008}]},{"c":[{"v":"19"},{"v":21.91410472}]},{"c":[{"v":"19"},{"v":21.271367688}]},{"c":[{"v":"19"},{"v":21.73800448}]},{"c":[{"v":"19"},{"v":21.624337792}]},{"c":[{"v":"19"},{"v":22.234370184}]},{"c":[{"v":"19"},{"v":21.986483744}]},{"c":[{"v":"19"},{"v":21.429663872}]},{"c":[{"v":"19"},{"v":21.461505432}]},{"c":[{"v":"19"},{"v":21.372322488}]},{"c":[{"v":"19"},{"v":21.5558458}]},{"c":[{"v":"20"},{"v":21.738044408}]},{"c":[{"v":"20"},{"v":22.65151672}]},{"c":[{"v":"20"},{"v":23.074601192}]},{"c":[{"v":"20"},{"v":22.5706468}]},{"c":[{"v":"20"},{"v":22.905384688}]},{"c":[{"v":"20"},{"v":23.257924872}]},{"c":[{"v":"20"},{"v":22.83492668}]},{"c":[{"v":"20"},{"v":22.883755272}]},{"c":[{"v":"20"},{"v":22.519870968}]},{"c":[{"v":"20"},{"v":22.476947432}]},{"c":[{"v":"20"},{"v":21.999016}]},{"c":[{"v":"20"},{"v":22.850216256}]},{"c":[{"v":"21"},{"v":22.76059876}]},{"c":[{"v":"21"},{"v":22.817794272}]},{"c":[{"v":"21"},{"v":22.23472104}]},{"c":[{"v":"21"},{"v":22.066481472}]},{"c":[{"v":"21"},{"v":21.800579408}]},{"c":[{"v":"21"},{"v":21.731285856}]},{"c":[{"v":"21"},{"v":21.91862104}]},{"c":[{"v":"21"},{"v":22.100601904}]},{"c":[{"v":"21"},{"v":21.369085248}]},{"c":[{"v":"21"},{"v":21.601847568}]},{"c":[{"v":"21"},{"v":21.406120024}]},{"c":[{"v":"21"},{"v":21.62535232}]},{"c":[{"v":"22"},{"v":20.944015816}]},{"c":[{"v":"22"},{"v":19.775992472}]},{"c":[{"v":"22"},{"v":19.689763288}]},{"c":[{"v":"22"},{"v":19.232343248}]},{"c":[{"v":"22"},{"v":19.229646568}]},{"c":[{"v":"22"},{"v":19.0495668}]},{"c":[{"v":"22"},{"v":18.876369128}]},{"c":[{"v":"22"},{"v":19.186025456}]},{"c":[{"v":"22"},{"v":18.435713528}]},{"c":[{"v":"22"},{"v":17.876489056}]},{"c":[{"v":"22"},{"v":17.294672816}]},{"c":[{"v":"22"},{"v":17.393125024}]},{"c":[{"v":"23"},{"v":17.292578704}]},{"c":[{"v":"23"},{"v":16.507565264}]},{"c":[{"v":"23"},{"v":16.193390576}]},{"c":[{"v":"23"},{"v":16.079084992}]},{"c":[{"v":"23"},{"v":15.821411976}]},{"c":[{"v":"23"},{"v":15.417636736}]},{"c":[{"v":"23"},{"v":15.119208144}]},{"c":[{"v":"23"},{"v":14.756204304}]},{"c":[{"v":"23"},{"v":14.718177784}]},{"c":[{"v":"23"},{"v":14.467763464}]},{"c":[{"v":"23"},{"v":14.135295904}]},{"c":[{"v":"23"},{"v":13.57441508}]},{"c":[{"v":"00"},{"v":13.18136604}]},{"c":[{"v":"00"},{"v":12.989545952}]},{"c":[{"v":"00"},{"v":12.18238728}]},{"c":[{"v":"00"},{"v":11.964208712}]},{"c":[{"v":"00"},{"v":11.581377328}]},{"c":[{"v":"00"},{"v":11.382002912}]},{"c":[{"v":"00"},{"v":11.44368908}]},{"c":[{"v":"00"},{"v":11.158015416}]},{"c":[{"v":"00"},{"v":10.76571388}]},{"c":[{"v":"00"},{"v":10.881498032}]},{"c":[{"v":"00"},{"v":10.342552976}]},{"c":[{"v":"00"},{"v":10.08775196}]},{"c":[{"v":"01"},{"v":10.041697448}]},{"c":[{"v":"01"},{"v":9.469350712}]},{"c":[{"v":"01"},{"v":9.496925976}]},{"c":[{"v":"01"},{"v":9.16992428}]},{"c":[{"v":"01"},{"v":9.312772144}]},{"c":[{"v":"01"},{"v":8.722561584}]},{"c":[{"v":"01"},{"v":8.555558664}]},{"c":[{"v":"01"},{"v":8.46607368}]},{"c":[{"v":"01"},{"v":8.2416146}]},{"c":[{"v":"01"},{"v":8.224701144}]},{"c":[{"v":"01"},{"v":7.899675968}]},{"c":[{"v":"01"},{"v":7.806615832}]},{"c":[{"v":"02"},{"v":7.56866528}]},{"c":[{"v":"02"},{"v":7.587791488}]},{"c":[{"v":"02"},{"v":7.555799768}]},{"c":[{"v":"02"},{"v":7.474522024}]},{"c":[{"v":"02"},{"v":7.317214208}]},{"c":[{"v":"02"},{"v":7.111779272}]},{"c":[{"v":"02"},{"v":6.977598728}]},{"c":[{"v":"02"},{"v":6.783426}]},{"c":[{"v":"02"},{"v":6.7049334}]},{"c":[{"v":"02"},{"v":6.27368104}]},{"c":[{"v":"02"},{"v":6.113979384}]},{"c":[{"v":"02"},{"v":6.3429046}]},{"c":[{"v":"03"},{"v":6.13792176}]},{"c":[{"v":"03"},{"v":6.274421576}]},{"c":[{"v":"03"},{"v":6.209545032}]},{"c":[{"v":"03"},{"v":6.04427288}]},{"c":[{"v":"03"},{"v":6.280275248}]},{"c":[{"v":"03"},{"v":6.157925112}]},{"c":[{"v":"03"},{"v":5.73679228}]},{"c":[{"v":"03"},{"v":5.893480048}]},{"c":[{"v":"03"},{"v":5.631293656}]},{"c":[{"v":"03"},{"v":5.685466696}]},{"c":[{"v":"03"},{"v":5.469723}]},{"c":[{"v":"03"},{"v":5.405200472}]},{"c":[{"v":"04"},{"v":5.629296584}]},{"c":[{"v":"04"},{"v":5.58994924}]},{"c":[{"v":"04"},{"v":5.43020136}]},{"c":[{"v":"04"},{"v":5.570935896}]},{"c":[{"v":"04"},{"v":5.37011964}]},{"c":[{"v":"04"},{"v":5.434179376}]},{"c":[{"v":"04"},{"v":5.435013}]},{"c":[{"v":"04"},{"v":5.402540536}]},{"c":[{"v":"04"},{"v":5.43732096}]},{"c":[{"v":"04"},{"v":5.311828288}]},{"c":[{"v":"04"},{"v":5.36415944}]},{"c":[{"v":"04"},{"v":5.366324816}]},{"c":[{"v":"05"},{"v":5.484580752}]},{"c":[{"v":"05"},{"v":5.265576096}]},{"c":[{"v":"05"},{"v":5.071091112}]},{"c":[{"v":"05"},{"v":5.267486864}]},{"c":[{"v":"05"},{"v":5.247637344}]},{"c":[{"v":"05"},{"v":5.2616468}]},{"c":[{"v":"05"},{"v":5.200863096}]},{"c":[{"v":"05"},{"v":5.291686256}]},{"c":[{"v":"05"},{"v":5.335136736}]},{"c":[{"v":"05"},{"v":5.311958864}]},{"c":[{"v":"05"},{"v":5.447663832}]},{"c":[{"v":"05"},{"v":5.422091216}]},{"c":[{"v":"06"},{"v":5.40434032}]},{"c":[{"v":"06"},{"v":5.480154112}]},{"c":[{"v":"06"},{"v":5.349737952}]},{"c":[{"v":"06"},{"v":5.428473992}]},{"c":[{"v":"06"},{"v":5.541391752}]},{"c":[{"v":"06"},{"v":5.426584624}]},{"c":[{"v":"06"},{"v":5.655472264}]},{"c":[{"v":"06"},{"v":5.742046184}]},{"c":[{"v":"06"},{"v":5.813908312}]},{"c":[{"v":"06"},{"v":5.901576024}]},{"c":[{"v":"06"},{"v":6.068898264}]},{"c":[{"v":"06"},{"v":6.46429004}]},{"c":[{"v":"07"},{"v":6.354583368}]},{"c":[{"v":"07"},{"v":6.695351472}]},{"c":[{"v":"07"},{"v":6.728641224}]},{"c":[{"v":"07"},{"v":6.998390824}]},{"c":[{"v":"07"},{"v":7.462439928}]},{"c":[{"v":"07"},{"v":7.559707456}]},{"c":[{"v":"07"},{"v":8.033641472}]},{"c":[{"v":"07"},{"v":8.554950904}]},{"c":[{"v":"07"},{"v":9.217418688}]},{"c":[{"v":"07"},{"v":9.554613384}]},{"c":[{"v":"07"},{"v":9.375210568}]},{"c":[{"v":"07"},{"v":9.745792024}]},{"c":[{"v":"08"},{"v":9.786224256}]},{"c":[{"v":"08"},{"v":10.578064512}]},{"c":[{"v":"08"},{"v":11.202526048}]},{"c":[{"v":"08"},{"v":11.215110696}]},{"c":[{"v":"08"},{"v":11.48238452}]},{"c":[{"v":"08"},{"v":11.844216384}]},{"c":[{"v":"08"},{"v":12.276485704}]},{"c":[{"v":"08"},{"v":12.520948688}]},{"c":[{"v":"08"},{"v":12.724276392}]},{"c":[{"v":"08"},{"v":13.073339568}]},{"c":[{"v":"08"},{"v":13.143464912}]},{"c":[{"v":"08"},{"v":13.499657336}]},{"c":[{"v":"09"},{"v":13.86991844}]},{"c":[{"v":"09"},{"v":14.646076432}]},{"c":[{"v":"09"},{"v":15.029495656}]},{"c":[{"v":"09"},{"v":15.496876168}]},{"c":[{"v":"09"},{"v":15.642393736}]},{"c":[{"v":"09"},{"v":15.455806864}]},{"c":[{"v":"09"},{"v":15.521560656}]},{"c":[{"v":"09"},{"v":15.704343592}]},{"c":[{"v":"09"},{"v":16.17109452}]},{"c":[{"v":"09"},{"v":16.30362496}]},{"c":[{"v":"09"},{"v":16.270570808}]},{"c":[{"v":"09"},{"v":16.394972712}]},{"c":[{"v":"10"},{"v":16.845580608}]},{"c":[{"v":"10"},{"v":17.369715904}]},{"c":[{"v":"10"},{"v":17.625654056}]},{"c":[{"v":"10"},{"v":17.620379424}]},{"c":[{"v":"10"},{"v":17.547957096}]},{"c":[{"v":"10"},{"v":17.445602016}]},{"c":[{"v":"10"},{"v":17.89099512}]},{"c":[{"v":"10"},{"v":17.961059336}]},{"c":[{"v":"10"},{"v":18.208935392}]},{"c":[{"v":"10"},{"v":18.35696124}]},{"c":[{"v":"10"},{"v":18.525942824}]},{"c":[{"v":"10"},{"v":18.256581168}]},{"c":[{"v":"11"},{"v":19.083241416}]},{"c":[{"v":"11"},{"v":19.094566216}]},{"c":[{"v":"11"},{"v":19.7908138}]},{"c":[{"v":"11"},{"v":20.11004668}]},{"c":[{"v":"11"},{"v":20.200520024}]},{"c":[{"v":"11"},{"v":19.532781048}]},{"c":[{"v":"11"},{"v":19.270815336}]},{"c":[{"v":"11"},{"v":19.408984432}]},{"c":[{"v":"11"},{"v":19.633112024}]},{"c":[{"v":"11"},{"v":19.676556744}]},{"c":[{"v":"11"},{"v":19.593574856}]},{"c":[{"v":"11"},{"v":19.505894264}]},{"c":[{"v":"12"},{"v":19.513875696}]},{"c":[{"v":"12"},{"v":19.509994392}]},{"c":[{"v":"12"},{"v":20.022867384}]},{"c":[{"v":"12"},{"v":19.119937552}]},{"c":[{"v":"12"},{"v":19.204587576}]},{"c":[{"v":"12"},{"v":19.23767372}]},{"c":[{"v":"12"},{"v":19.447646984}]},{"c":[{"v":"12"},{"v":19.433880968}]},{"c":[{"v":"12"},{"v":19.221581104}]},{"c":[{"v":"12"},{"v":19.512660232}]},{"c":[{"v":"12"},{"v":19.451876592}]},{"c":[{"v":"12"},{"v":19.873187168}]},{"c":[{"v":"13"},{"v":19.426813312}]},{"c":[{"v":"13"},{"v":19.617539672}]},{"c":[{"v":"13"},{"v":19.962792456}]},{"c":[{"v":"13"},{"v":19.977366856}]},{"c":[{"v":"13"},{"v":20.154768816}]},{"c":[{"v":"13"},{"v":20.449210424}]},{"c":[{"v":"13"},{"v":20.201020936}]},{"c":[{"v":"13"},{"v":20.386109472}]},{"c":[{"v":"13"},{"v":20.075931208}]},{"c":[{"v":"13"},{"v":20.12023728}]},{"c":[{"v":"13"},{"v":20.12190448}]},{"c":[{"v":"13"},{"v":20.040161464}]},{"c":[{"v":"14"},{"v":20.127161152}]},{"c":[{"v":"14"},{"v":19.718089408}]},{"c":[{"v":"14"},{"v":19.884119528}]},{"c":[{"v":"14"},{"v":20.107815488}]},{"c":[{"v":"14"},{"v":20.504483736}]},{"c":[{"v":"14"},{"v":20.00417736}]},{"c":[{"v":"14"},{"v":20.127771448}]},{"c":[{"v":"14"},{"v":20.136555472}]},{"c":[{"v":"14"},{"v":20.103360632}]},{"c":[{"v":"14"},{"v":19.955603696}]},{"c":[{"v":"14"},{"v":20.822928016}]},{"c":[{"v":"14"},{"v":20.59505536}]},{"c":[{"v":"15"},{"v":20.350023664}]},{"c":[{"v":"15"},{"v":19.930679576}]},{"c":[{"v":"15"},{"v":20.098098976}]},{"c":[{"v":"15"},{"v":20.113377168}]},{"c":[{"v":"15"},{"v":20.342733544}]},{"c":[{"v":"15"},{"v":20.2713646}]},{"c":[{"v":"15"},{"v":20.376986584}]},{"c":[{"v":"15"},{"v":20.407375704}]},{"c":[{"v":"15"},{"v":20.38940844}]},{"c":[{"v":"15"},{"v":20.51363876}]},{"c":[{"v":"15"},{"v":20.963947424}]},{"c":[{"v":"15"},{"v":20.745209176}]},{"c":[{"v":"16"},{"v":21.076504496}]},{"c":[{"v":"16"},{"v":20.927902248}]},{"c":[{"v":"16"},{"v":20.577103168}]},{"c":[{"v":"16"},{"v":21.003372832}]},{"c":[{"v":"16"},{"v":20.859415024}]},{"c":[{"v":"16"},{"v":21.243220088}]},{"c":[{"v":"16"},{"v":21.302838224}]},{"c":[{"v":"16"},{"v":21.177648168}]},{"c":[{"v":"16"},{"v":21.203697656}]},{"c":[{"v":"16"},{"v":22.101499664}]},{"c":[{"v":"16"},{"v":21.971418976}]},{"c":[{"v":"16"},{"v":21.699862296}]},{"c":[{"v":"16"},{"v":21.697133504}]},{"c":[{"v":"17"},{"v":21.745304704}]}]}