{"cols":[{"type":"string"},{"type":"number"}],"rows":[{"c":[{"v":"16"},{"v":17.677558848}]},{"c":[{"v":"16"},{"v":17.570773104}]},{"c":[{"v":"16"},{"v":18.226907224}]},{"c":[{"v":"16"},{"v":18.129158888}]},{"c":[{"v":"16"},{"v":17.78754004}]},{"c":[{"v":"16"},{"v":17.871046304}]},{"c":[{"v":"16"},{"v":18.36740404}]},{"c":[{"v":"16"},{"v":18.261255128}]},{"c":[{"v":"16"},{"v":18.3374512}]},{"c":[{"v":"16"},{"v":18.600243656}]},{"c":[{"v":"16"},{"v":18.522544544}]},{"c":[{"v":"17"},{"v":18.942724808}]},{"c":[{"v":"17"},{"v":18.2418534}]},{"c":[{"v":"17"},{"v":18.65307048}]},{"c":[{"v":"17"},{"v":18.442043544}]},{"c":[{"v":"17"},{"v":18.201993408}]},{"c":[{"v":"17"},{"v":18.884837096}]},{"c":[{"v":"17"},{"v":18.619151056}]},{"c":[{"v":"17"},{"v":18.718244296}]},{"c":[{"v":"17"},{"v":18.39729536}]},{"c":[{"v":"17"},{"v":18.847301056}]},{"c":[{"v":"17"},{"v":18.891936584}]},{"c":[{"v":"17"},{"v":19.079983848}]},{"c":[{"v":"18"},{"v":19.223407464}]},{"c":[{"v":"18"},{"v":19.02077244}]},{"c":[{"v":"18"},{"v":19.998160928}]},{"c":[{"v":"18"},{"v":20.215678456}]},{"c":[{"v":"18"},{"v":19.909508984}]},{"c":[{"v":"18"},{"v":19.874353968}]},{"c":[{"v":"18"},{"v":20.305753352}]},{"c":[{"v":"18"},{"v":20.758305304}]},{"c":[{"v":"18"},{"v":21.049402392}]},{"c":[{"v":"18"},{"v":20.870131608}]},{"c":[{"v":"18"},{"v":21.227604408}]},{"c":[{"v":"18"},{"v":21.335378504}]},{"c":[{"v":"19"},{"v":21.441506168}]},{"c":[{"v":"19"},{"v":22.187443712}]},{"c":[{"v":"19"},{"v":22.18661452}]},{"c":[{"v":"19"},{"v":22.388677488}]},{"c":[{"v":"19"},{"v":22.72567496}]},{"c":[{"v":"19"},{"v":22.750022544}]},{"c":[{"v":"19"},{"v":22.945792456}]},{"c":[{"v":"19"},{"v":22.745546672}]},{"c":[{"v":"19"},{"v":22.737295464}]},{"c":[{"v":"19"},{"v":23.525852736}]},{"c":[{"v":"19"},{"v":22.853627256}]},{"c":[{"v":"19"},{"v":23.910104488}]},{"c":[{"v":"20"},{"v":23.942969792}]},{"c":[{"v":"20"},{"v":24.85353992}]},{"c":[{"v":"20"},{"v":24.707123904}]},{"c":[{"v":"20"},{"v":24.670405192}]},{"c":[{"v":"20"},{"v":24.67793728}]},{"c":[{"v":"20"},{"v":24.1419006}]},{"c":[{"v":"20"},{"v":24.646717824}]},{"c":[{"v":"20"},{"v":24.905619608}]},{"c":[{"v":"20"},{"v":24.334289488}]},{"c":[{"v":"20"},{"v":24.6219462}]},{"c":[{"v":"20"},{"v":24.22161292}]},{"c":[{"v":"20"},{"v":24.278516184}]},{"c":[{"v":"21"},{"v":24.504004616}]},{"c":[{"v":"21"},{"v":23.997549304}]},{"c":[{"v":"21"},{"v":23.794993096}]},{"c":[{"v":"21"},{"v":23.932364456}]},{"c":[{"v":"21"},{"v":24.32229744}]},{"c":[{"v":"21"},{"v":24.2802388}]},{"c":[{"v":"21"},{"v":23.788513008}]},{"c":[{"v":"21"},{"v":24.241438408}]},{"c":[{"v":"21"},{"v":23.886808512}]},{"c":[{"v":"21"},{"v":23.986310952}]},{"c":[{"v":"21"},{"v":22.967352056}]},{"c":[{"v":"21"},{"v":22.705825136}]},{"c":[{"v":"22"},{"v":22.619584096}]},{"c":[{"v":"22"},{"v":22.150515328}]},{"c":[{"v":"22"},{"v":22.156011816}]},{"c":[{"v":"22"},{"v":21.372293072}]},{"c":[{"v":"22"},{"v":21.512124264}]},{"c":[{"v":"22"},{"v":21.25156328}]},{"c":[{"v":"22"},{"v":20.610145104}]},{"c":[{"v":"22"},{"v":20.460050616}]},{"c":[{"v":"22"},{"v":19.95389172}]},{"c":[{"v":"22"},{"v":19.630537856}]},{"c":[{"v":"22"},{"v":19.530150432}]},{"c":[{"v":"22"},{"v":19.07192088}]},{"c":[{"v":"23"},{"v":18.507247056}]},{"c":[{"v":"23"},{"v":18.293357712}]},{"c":[{"v":"23"},{"v":17.953616064}]},{"c":[{"v":"23"},{"v":17.053011016}]},{"c":[{"v":"23"},{"v":17.002245408}]},{"c":[{"v":"23"},{"v":16.51435736}]},{"c":[{"v":"23"},{"v":15.991415944}]},{"c":[{"v":"23"},{"v":15.818993992}]},{"c":[{"v":"23"},{"v":15.270174064}]},{"c":[{"v":"23"},{"v":14.83405292}]},{"c":[{"v":"23"},{"v":14.173499512}]},{"c":[{"v":"23"},{"v":13.755800104}]},{"c":[{"v":"00"},{"v":13.462927296}]},{"c":[{"v":"00"},{"v":13.521018624}]},{"c":[{"v":"00"},{"v":13.02513972}]},{"c":[{"v":"00"},{"v":12.948806208}]},{"c":[{"v":"00"},{"v":12.41683592}]},{"c":[{"v":"00"},{"v":12.146963528}]},{"c":[{"v":"00"},{"v":11.805559424}]},{"c":[{"v":"00"},{"v":11.577417816}]},{"c":[{"v":"00"},{"v":11.169246072}]},{"c":[{"v":"00"},{"v":10.98401}]},{"c":[{"v":"00"},{"v":10.628090176}]},{"c":[{"v":"00"},{"v":10.140192264}]},{"c":[{"v":"01"},{"v":9.979424656}]},{"c":[{"v":"01"},{"v":9.90150204}]},{"c":[{"v":"01"},{"v":9.455410048}]},{"c":[{"v":"01"},{"v":9.366690856}]},{"c":[{"v":"01"},{"v":8.757933064}]},{"c":[{"v":"01"},{"v":8.86579172}]},{"c":[{"v":"01"},{"v":8.586765104}]},{"c":[{"v":"01"},{"v":8.588282264}]},{"c":[{"v":"01"},{"v":8.411263}]},{"c":[{"v":"01"},{"v":8.131589552}]},{"c":[{"v":"01"},{"v":7.86738628}]},{"c":[{"v":"01"},{"v":7.845803568}]},{"c":[{"v":"02"},{"v":7.611870568}]},{"c":[{"v":"02"},{"v":7.607564016}]},{"c":[{"v":"02"},{"v":7.212098208}]},{"c":[{"v":"02"},{"v":7.216373536}]},{"c":[{"v":"02"},{"v":7.354719656}]},{"c":[{"v":"02"},{"v":6.98183228}]},{"c":[{"v":"02"},{"v":6.80715024}]},{"c":[{"v":"02"},{"v":6.798361536}]},{"c":[{"v":"02"},{"v":6.707936664}]},{"c":[{"v":"02"},{"v":6.557934424}]},{"c":[{"v":"02"},{"v":6.347006344}]},{"c":[{"v":"02"},{"v":6.282229816}]},{"c":[{"v":"03"},{"v":6.081524056}]},{"c":[{"v":"03"},{"v":6.452998864}]},{"c":[{"v":"03"},{"v":6.229060768}]},{"c":[{"v":"03"},{"v":6.208881648}]},{"c":[{"v":"03"},{"v":6.04226932}]},{"c":[{"v":"03"},{"v":6.1590396}]},{"c":[{"v":"03"},{"v":6.025224248}]},{"c":[{"v":"03"},{"v":6.036181464}]},{"c":[{"v":"03"},{"v":6.100782208}]},{"c":[{"v":"03"},{"v":6.129398488}]},{"c":[{"v":"03"},{"v":6.113949808}]},{"c":[{"v":"03"},{"v":5.909978296}]},{"c":[{"v":"04"},{"v":5.825059112}]},{"c":[{"v":"04"},{"v":5.892267656}]},{"c":[{"v":"04"},{"v":5.724103576}]},{"c":[{"v":"04"},{"v":5.681389048}]},{"c":[{"v":"04"},{"v":5.656724344}]},{"c":[{"v":"04"},{"v":5.702591168}]},{"c":[{"v":"04"},{"v":5.850500864}]},{"c":[{"v":"04"},{"v":6.038566744}]},{"c":[{"v":"04"},{"v":5.840063032}]},{"c":[{"v":"04"},{"v":5.918583464}]},{"c":[{"v":"04"},{"v":5.5980868}]},{"c":[{"v":"04"},{"v":5.430097272}]},{"c":[{"v":"05"},{"v":5.35571532}]},{"c":[{"v":"05"},{"v":5.45902992}]},{"c":[{"v":"05"},{"v":5.3438938}]},{"c":[{"v":"05"},{"v":5.490558728}]},{"c":[{"v":"05"},{"v":5.45622748}]},{"c":[{"v":"05"},{"v":5.679932448}]},{"c":[{"v":"05"},{"v":5.729049128}]},{"c":[{"v":"05"},{"v":5.82830408}]},{"c":[{"v":"05"},{"v":5.797994912}]},{"c":[{"v":"05"},{"v":5.723808}]},{"c":[{"v":"05"},{"v":5.916492992}]},{"c":[{"v":"05"},{"v":6.006806728}]},{"c":[{"v":"06"},{"v":6.155930936}]},{"c":[{"v":"06"},{"v":6.544614968}]},{"c":[{"v":"06"},{"v":6.478316592}]},{"c":[{"v":"06"},{"v":6.744882464}]},{"c":[{"v":"06"},{"v":6.897815872}]},{"c":[{"v":"06"},{"v":7.262138888}]},{"c":[{"v":"06"},{"v":7.264933336}]},{"c":[{"v":"06"},{"v":7.483169048}]},{"c":[{"v":"06"},{"v":7.725455432}]},{"c":[{"v":"06"},{"v":7.928293512}]},{"c":[{"v":"06"},{"v":8.560500568}]},{"c":[{"v":"06"},{"v":8.75605676}]},{"c":[{"v":"07"},{"v":9.042249968}]},{"c":[{"v":"07"},{"v":9.538151456}]},{"c":[{"v":"07"},{"v":9.714017904}]},{"c":[{"v":"07"},{"v":10.146606552}]},{"c":[{"v":"07"},{"v":10.582767056}]},{"c":[{"v":"07"},{"v":10.674030512}]},{"c":[{"v":"07"},{"v":11.76219952}]},{"c":[{"v":"07"},{"v":11.344434688}]},{"c":[{"v":"07"},{"v":11.883262248}]},{"c":[{"v":"07"},{"v":12.10887552}]},{"c":[{"v":"07"},{"v":12.502199264}]},{"c":[{"v":"07"},{"v":12.66970924}]},{"c":[{"v":"08"},{"v":13.217150488}]},{"c":[{"v":"08"},{"v":13.64947608}]},{"c":[{"v":"08"},{"v":13.828137688}]},{"c":[{"v":"08"},{"v":14.033564664}]},{"c":[{"v":"08"},{"v":14.297288272}]},{"c":[{"v":"08"},{"v":14.596932856}]},{"c":[{"v":"08"},{"v":14.858328712}]},{"c":[{"v":"08"},{"v":14.814227064}]},{"c":[{"v":"08"},{"v":15.140735752}]},{"c":[{"v":"08"},{"v":15.588536472}]},{"c":[{"v":"08"},{"v":15.680852592}]},{"c":[{"v":"08"},{"v":15.698261576}]},{"c":[{"v":"09"},{"v":15.839160768}]},{"c":[{"v":"09"},{"v":16.273274464}]},{"c":[{"v":"09"},{"v":16.421481168}]},{"c":[{"v":"09"},{"v":16.588577936}]},{"c":[{"v":"09"},{"v":16.513085752}]},{"c":[{"v":"09"},{"v":16.853097672}]},{"c":[{"v":"09"},{"v":17.13225724}]},{"c":[{"v":"09"},{"v":17.479665304}]},{"c":[{"v":"09"},{"v":16.857059776}]},{"c":[{"v":"09"},{"v":17.23504056}]},{"c":[{"v":"09"},{"v":17.421332072}]},{"c":[{"v":"09"},{"v":18.159362648}]},{"c":[{"v":"10"},{"v":17.8731136}]},{"c":[{"v":"10"},{"v":18.560149064}]},{"c":[{"v":"10"},{"v":18.675492616}]},{"c":[{"v":"10"},{"v":18.518940536}]},{"c":[{"v":"10"},{"v":18.740486328}]},{"c":[{"v":"10"},{"v":18.895469008}]},{"c":[{"v":"10"},{"v":18.903099024}]},{"c":[{"v":"10"},{"v":19.529094896}]},{"c":[{"v":"10"},{"v":18.94331176}]},{"c":[{"v":"10"},{"v":18.920884816}]},{"c":[{"v":"10"},{"v":19.131563192}]},{"c":[{"v":"10"},{"v":19.582731384}]},{"c":[{"v":"11"},{"v":19.57764748}]},{"c":[{"v":"11"},{"v":19.244795152}]},{"c":[{"v":"11"},{"v":18.681027112}]},{"c":[{"v":"11"},{"v":19.256398256}]},{"c":[{"v":"11"},{"v":19.146685184}]},{"c":[{"v":"11"},{"v":19.179525144}]},{"c":[{"v":"11"},{"v":19.11739184}]},{"c":[{"v":"11"},{"v":19.122765976}]},{"c":[{"v":"11"},{"v":18.986257024}]},{"c":[{"v":"11"},{"v":19.453820472}]},{"c":[{"v":"11"},{"v":19.641698872}]},{"c":[{"v":"11"},{"v":19.407250632}]},{"c":[{"v":"12"},{"v":19.605925288}]},{"c":[{"v":"12"},{"v":19.706430984}]},{"c":[{"v":"12"},{"v":19.565834376}]},{"c":[{"v":"12"},{"v":19.660306152}]},{"c":[{"v":"12"},{"v":20.159752464}]},{"c":[{"v":"12"},{"v":19.831374032}]},{"c":[{"v":"12"},{"v":19.745927024}]},{"c":[{"v":"12"},{"v":19.710132}]},{"c":[{"v":"12"},{"v":19.630315048}]},{"c":[{"v":"12"},{"v":19.902735768}]},{"c":[{"v":"12"},{"v":19.936048272}]},{"c":[{"v":"12"},{"v":19.851261584}]},{"c":[{"v":"13"},{"v":19.211360824}]},{"c":[{"v":"13"},{"v":19.327411064}]},{"c":[{"v":"13"},{"v":19.26854624}]},{"c":[{"v":"13"},{"v":19.651575312}]},{"c":[{"v":"13"},{"v":19.45853492}]},{"c":[{"v":"13"},{"v":19.394711784}]},{"c":[{"v":"13"},{"v":19.453629736}]},{"c":[{"v":"13"},{"v":19.201062648}]},{"c":[{"v":"13"},{"v":19.478342048}]},{"c":[{"v":"13"},{"v":19.801639984}]},{"c":[{"v":"13"},{"v":19.20483084}]},{"c":[{"v":"13"},{"v":19.396162168}]},{"c":[{"v":"14"},{"v":19.17088448}]},{"c":[{"v":"14"},{"v":19.241113472}]},{"c":[{"v":"14"},{"v":19.197196904}]},{"c":[{"v":"14"},{"v":19.456974824}]},{"c":[{"v":"14"},{"v":19.159078736}]},{"c":[{"v":"14"},{"v":19.405207336}]},{"c":[{"v":"14"},{"v":18.981484496}]},{"c":[{"v":"14"},{"v":19.369291784}]},{"c":[{"v":"14"},{"v":19.293282592}]},{"c":[{"v":"14"},{"v":19.430464576}]},{"c":[{"v":"14"},{"v":19.5976816}]},{"c":[{"v":"14"},{"v":19.268665624}]},{"c":[{"v":"15"},{"v":19.804312568}]},{"c":[{"v":"15"},{"v":19.7304896}]},{"c":[{"v":"15"},{"v":19.611098256}]},{"c":[{"v":"15"},{"v":19.945108848}]},{"c":[{"v":"15"},{"v":19.46858912}]},{"c":[{"v":"15"},{"v":19.771798544}]},{"c":[{"v":"15"},{"v":19.494703952}]},{"c":[{"v":"15"},{"v":20.194837064}]},{"c":[{"v":"15"},{"v":20.186579728}]},{"c":[{"v":"15"},{"v":19.742469464}]},{"c":[{"v":"15"},{"v":19.600482024}]},{"c":[{"v":"15"},{"v":19.392640144}]},{"c":[{"v":"16"},{"v":19.643435392}]},{"c":[{"v":"16"},{"v":19.83383576}]},{"c":[{"v":"16"},{"v":19.33286076}]},{"c":[{"v":"16"},{"v":19.698127376}]},{"c":[{"v":"16"},{"v":19.498958256}]},{"c":[{"v":"16"},{"v":20.007451792}]},{"c":[{"v":"16"},{"v":19.583414176}]},{"c":[{"v":"16"},{"v":19.756563768}]},{"c":[{"v":"16"},{"v":19.572215352}]},{"c":[{"v":"16"},{"v":19.435716272}]},{"c":[{"v":"16"},{"v":19.649963072}]},{"c":[{"v":"16"},{"v":19.64475972}]},{"c":[{"v":"17"},{"v":19.914081728}]},{"c":[{"v":"17"},{"v":19.947085776}]},{"c":[{"v":"17"},{"v":19.801489688}]},{"c":[{"v":"17"},{"v":19.703542368}]},{"c":[{"v":"17"},{"v":19.866061688}]},{"c":[{"v":"17"},{"v":19.942839176}]},{"c":[{"v":"17"},{"v":19.781612336}]},{"c":[{"v":"17"},{"v":20.109479744}]},{"c":[{"v":"17"},{"v":19.753201136}]},{"c":[{"v":"17"},{"v":19.82347008}]},{"c":[{"v":"17"},{"v":20.429431416}]},{"c":[{"v":"17"},{"v":20.523072808}]},{"c":[{"v":"17"},{"v":20.523674008}]},{"c":[{"v":"18"},{"v":20.651402216}]}]}