{"cols":[{"type":"string"},{"type":"number"}],"rows":[{"c":[{"v":"00"},{"v":171.718316592}]},{"c":[{"v":"00"},{"v":166.743522472}]},{"c":[{"v":"00"},{"v":158.47455528}]},{"c":[{"v":"00"},{"v":153.273719048}]},{"c":[{"v":"00"},{"v":146.902729944}]},{"c":[{"v":"00"},{"v":141.450520736}]},{"c":[{"v":"00"},{"v":136.80353184}]},{"c":[{"v":"00"},{"v":131.935620664}]},{"c":[{"v":"00"},{"v":127.178663888}]},{"c":[{"v":"00"},{"v":122.16274312}]},{"c":[{"v":"00"},{"v":119.638241144}]},{"c":[{"v":"01"},{"v":115.652505064}]},{"c":[{"v":"01"},{"v":113.656707056}]},{"c":[{"v":"01"},{"v":110.366200696}]},{"c":[{"v":"01"},{"v":110.43040948}]},{"c":[{"v":"01"},{"v":108.601654856}]},{"c":[{"v":"01"},{"v":105.684123544}]},{"c":[{"v":"01"},{"v":102.525723528}]},{"c":[{"v":"01"},{"v":102.17526472}]},{"c":[{"v":"01"},{"v":98.349602976}]},{"c":[{"v":"01"},{"v":95.062129624}]},{"c":[{"v":"01"},{"v":93.259845128}]},{"c":[{"v":"01"},{"v":90.804056472}]},{"c":[{"v":"02"},{"v":87.170629112}]},{"c":[{"v":"02"},{"v":89.941345352}]},{"c":[{"v":"02"},{"v":86.59215036}]},{"c":[{"v":"02"},{"v":84.377564264}]},{"c":[{"v":"02"},{"v":82.894720088}]},{"c":[{"v":"02"},{"v":81.227575576}]},{"c":[{"v":"02"},{"v":77.177768576}]},{"c":[{"v":"02"},{"v":78.240345672}]},{"c":[{"v":"02"},{"v":77.046369432}]},{"c":[{"v":"02"},{"v":75.984063728}]},{"c":[{"v":"02"},{"v":74.17020856}]},{"c":[{"v":"02"},{"v":72.04856864}]},{"c":[{"v":"03"},{"v":70.021764744}]},{"c":[{"v":"03"},{"v":73.00443616}]},{"c":[{"v":"03"},{"v":71.343514936}]},{"c":[{"v":"03"},{"v":70.564844136}]},{"c":[{"v":"03"},{"v":69.939654736}]},{"c":[{"v":"03"},{"v":68.467142744}]},{"c":[{"v":"03"},{"v":67.994766648}]},{"c":[{"v":"03"},{"v":69.091272312}]},{"c":[{"v":"03"},{"v":69.030858984}]},{"c":[{"v":"03"},{"v":67.652788736}]},{"c":[{"v":"03"},{"v":67.371812568}]},{"c":[{"v":"03"},{"v":66.526382472}]},{"c":[{"v":"04"},{"v":67.140201368}]},{"c":[{"v":"04"},{"v":69.297063616}]},{"c":[{"v":"04"},{"v":67.780618448}]},{"c":[{"v":"04"},{"v":68.060624272}]},{"c":[{"v":"04"},{"v":70.69017772}]},{"c":[{"v":"04"},{"v":71.94037924}]},{"c":[{"v":"04"},{"v":72.501609064}]},{"c":[{"v":"04"},{"v":74.021653496}]},{"c":[{"v":"04"},{"v":71.26861756}]},{"c":[{"v":"04"},{"v":73.673458616}]},{"c":[{"v":"04"},{"v":72.615862992}]},{"c":[{"v":"04"},{"v":73.365836552}]},{"c":[{"v":"05"},{"v":74.543773632}]},{"c":[{"v":"05"},{"v":77.302449184}]},{"c":[{"v":"05"},{"v":76.6502204}]},{"c":[{"v":"05"},{"v":78.299902024}]},{"c":[{"v":"05"},{"v":78.196820728}]},{"c":[{"v":"05"},{"v":78.667393088}]},{"c":[{"v":"05"},{"v":78.56080032}]},{"c":[{"v":"05"},{"v":80.97285996}]},{"c":[{"v":"05"},{"v":83.06567612}]},{"c":[{"v":"05"},{"v":84.395176688}]},{"c":[{"v":"05"},{"v":87.865390624}]},{"c":[{"v":"05"},{"v":90.816552296}]},{"c":[{"v":"06"},{"v":94.797346048}]},{"c":[{"v":"06"},{"v":102.530669072}]},{"c":[{"v":"06"},{"v":108.440793928}]},{"c":[{"v":"06"},{"v":110.296258656}]},{"c":[{"v":"06"},{"v":113.618157888}]},{"c":[{"v":"06"},{"v":117.487341536}]},{"c":[{"v":"06"},{"v":121.1683836}]},{"c":[{"v":"06"},{"v":129.388795232}]},{"c":[{"v":"06"},{"v":135.860530528}]},{"c":[{"v":"06"},{"v":143.426413128}]},{"c":[{"v":"06"},{"v":148.060031904}]},{"c":[{"v":"06"},{"v":157.343943392}]},{"c":[{"v":"07"},{"v":166.4980856}]},{"c":[{"v":"07"},{"v":179.629196856}]},{"c":[{"v":"07"},{"v":187.568807152}]},{"c":[{"v":"07"},{"v":192.826412208}]},{"c":[{"v":"07"},{"v":196.087586256}]},{"c":[{"v":"07"},{"v":194.296081632}]},{"c":[{"v":"07"},{"v":194.144832576}]},{"c":[{"v":"07"},{"v":196.10301112}]},{"c":[{"v":"07"},{"v":199.747423672}]},{"c":[{"v":"07"},{"v":201.762001664}]},{"c":[{"v":"07"},{"v":203.366965872}]},{"c":[{"v":"07"},{"v":209.227799256}]},{"c":[{"v":"08"},{"v":212.799941616}]},{"c":[{"v":"08"},{"v":220.970662984}]},{"c":[{"v":"08"},{"v":226.472308496}]},{"c":[{"v":"08"},{"v":227.493887288}]},{"c":[{"v":"08"},{"v":227.494894656}]},{"c":[{"v":"08"},{"v":227.641901344}]},{"c":[{"v":"08"},{"v":227.400025992}]},{"c":[{"v":"08"},{"v":231.864878088}]},{"c":[{"v":"08"},{"v":235.420432168}]},{"c":[{"v":"08"},{"v":237.53730256}]},{"c":[{"v":"08"},{"v":237.327891464}]},{"c":[{"v":"08"},{"v":238.982934824}]},{"c":[{"v":"09"},{"v":241.695986832}]},{"c":[{"v":"09"},{"v":244.558437328}]},{"c":[{"v":"09"},{"v":244.480799464}]},{"c":[{"v":"09"},{"v":245.751090384}]},{"c":[{"v":"09"},{"v":245.717437152}]},{"c":[{"v":"09"},{"v":243.671937456}]},{"c":[{"v":"09"},{"v":244.723053304}]},{"c":[{"v":"09"},{"v":244.275871856}]},{"c":[{"v":"09"},{"v":242.09542244}]},{"c":[{"v":"09"},{"v":241.325538056}]},{"c":[{"v":"09"},{"v":240.085677288}]},{"c":[{"v":"09"},{"v":239.477441592}]},{"c":[{"v":"10"},{"v":240.584016816}]},{"c":[{"v":"10"},{"v":242.9481814}]},{"c":[{"v":"10"},{"v":245.793047072}]},{"c":[{"v":"10"},{"v":244.62632688}]},{"c":[{"v":"10"},{"v":248.549211528}]},{"c":[{"v":"10"},{"v":246.084860784}]},{"c":[{"v":"10"},{"v":244.622334712}]},{"c":[{"v":"10"},{"v":244.449606848}]},{"c":[{"v":"10"},{"v":243.627775768}]},{"c":[{"v":"10"},{"v":245.489238288}]},{"c":[{"v":"10"},{"v":243.747618608}]},{"c":[{"v":"10"},{"v":246.726095048}]},{"c":[{"v":"11"},{"v":245.69497328}]},{"c":[{"v":"11"},{"v":248.419514696}]},{"c":[{"v":"11"},{"v":248.380159216}]},{"c":[{"v":"11"},{"v":248.768005744}]},{"c":[{"v":"11"},{"v":246.362168}]},{"c":[{"v":"11"},{"v":246.046486232}]},{"c":[{"v":"11"},{"v":243.790756256}]},{"c":[{"v":"11"},{"v":243.668906464}]},{"c":[{"v":"11"},{"v":242.047545456}]},{"c":[{"v":"11"},{"v":237.81562164}]},{"c":[{"v":"11"},{"v":240.746639192}]},{"c":[{"v":"11"},{"v":241.98106472}]},{"c":[{"v":"12"},{"v":243.029135328}]},{"c":[{"v":"12"},{"v":246.871476192}]},{"c":[{"v":"12"},{"v":244.95087156}]},{"c":[{"v":"12"},{"v":244.462029224}]},{"c":[{"v":"12"},{"v":244.537348616}]},{"c":[{"v":"12"},{"v":246.003780896}]},{"c":[{"v":"12"},{"v":248.614498032}]},{"c":[{"v":"12"},{"v":247.704795088}]},{"c":[{"v":"12"},{"v":249.911294072}]},{"c":[{"v":"12"},{"v":248.297523808}]},{"c":[{"v":"12"},{"v":249.246013344}]},{"c":[{"v":"12"},{"v":250.51795344}]},{"c":[{"v":"13"},{"v":254.079744096}]},{"c":[{"v":"13"},{"v":255.170552048}]},{"c":[{"v":"13"},{"v":254.608716744}]},{"c":[{"v":"13"},{"v":253.995446224}]},{"c":[{"v":"13"},{"v":256.768672448}]},{"c":[{"v":"13"},{"v":257.311152472}]},{"c":[{"v":"13"},{"v":255.424892144}]},{"c":[{"v":"13"},{"v":255.453840824}]},{"c":[{"v":"13"},{"v":257.873331088}]},{"c":[{"v":"13"},{"v":255.821077456}]},{"c":[{"v":"13"},{"v":256.948277192}]},{"c":[{"v":"13"},{"v":258.967527792}]},{"c":[{"v":"14"},{"v":262.160870144}]},{"c":[{"v":"14"},{"v":262.381837424}]},{"c":[{"v":"14"},{"v":261.366363864}]},{"c":[{"v":"14"},{"v":262.296806224}]},{"c":[{"v":"14"},{"v":265.923095736}]},{"c":[{"v":"14"},{"v":265.400399424}]},{"c":[{"v":"14"},{"v":266.783238264}]},{"c":[{"v":"14"},{"v":268.461101704}]},{"c":[{"v":"14"},{"v":269.438223512}]},{"c":[{"v":"14"},{"v":269.740889184}]},{"c":[{"v":"14"},{"v":270.47550776}]},{"c":[{"v":"14"},{"v":272.62321724}]},{"c":[{"v":"15"},{"v":269.369611272}]},{"c":[{"v":"15"},{"v":272.466608528}]},{"c":[{"v":"15"},{"v":274.386051752}]},{"c":[{"v":"15"},{"v":274.383530184}]},{"c":[{"v":"15"},{"v":273.815662568}]},{"c":[{"v":"15"},{"v":273.852437976}]},{"c":[{"v":"15"},{"v":274.222436056}]},{"c":[{"v":"15"},{"v":271.399074968}]},{"c":[{"v":"15"},{"v":272.858349792}]},{"c":[{"v":"15"},{"v":271.397434664}]},{"c":[{"v":"15"},{"v":274.093385176}]},{"c":[{"v":"15"},{"v":274.217267224}]},{"c":[{"v":"16"},{"v":278.571343328}]},{"c":[{"v":"16"},{"v":278.60864664}]},{"c":[{"v":"16"},{"v":279.263365528}]},{"c":[{"v":"16"},{"v":277.858231952}]},{"c":[{"v":"16"},{"v":280.738616048}]},{"c":[{"v":"16"},{"v":279.191193888}]},{"c":[{"v":"16"},{"v":279.322477048}]},{"c":[{"v":"16"},{"v":279.54306556}]},{"c":[{"v":"16"},{"v":279.550304408}]},{"c":[{"v":"16"},{"v":278.647730072}]},{"c":[{"v":"16"},{"v":277.493166256}]},{"c":[{"v":"16"},{"v":279.494045312}]},{"c":[{"v":"17"},{"v":283.099036856}]},{"c":[{"v":"17"},{"v":280.974810464}]},{"c":[{"v":"17"},{"v":283.259495832}]},{"c":[{"v":"17"},{"v":282.47859376}]},{"c":[{"v":"17"},{"v":283.168721768}]},{"c":[{"v":"17"},{"v":283.869112264}]},{"c":[{"v":"17"},{"v":283.049484008}]},{"c":[{"v":"17"},{"v":286.339061296}]},{"c":[{"v":"17"},{"v":284.581420096}]},{"c":[{"v":"17"},{"v":284.195660696}]},{"c":[{"v":"17"},{"v":286.494705184}]},{"c":[{"v":"17"},{"v":288.356067032}]},{"c":[{"v":"18"},{"v":285.89584768}]},{"c":[{"v":"18"},{"v":289.694415848}]},{"c":[{"v":"18"},{"v":292.13836628}]},{"c":[{"v":"18"},{"v":297.68467816}]},{"c":[{"v":"18"},{"v":299.532907072}]},{"c":[{"v":"18"},{"v":300.412266064}]},{"c":[{"v":"18"},{"v":300.431564352}]},{"c":[{"v":"18"},{"v":302.996712312}]},{"c":[{"v":"18"},{"v":301.407967384}]},{"c":[{"v":"18"},{"v":307.412948392}]},{"c":[{"v":"18"},{"v":313.420221256}]},{"c":[{"v":"18"},{"v":318.53123244}]},{"c":[{"v":"19"},{"v":325.613124304}]},{"c":[{"v":"19"},{"v":332.94550516}]},{"c":[{"v":"19"},{"v":344.652010144}]},{"c":[{"v":"19"},{"v":354.493352464}]},{"c":[{"v":"19"},{"v":359.586131488}]},{"c":[{"v":"19"},{"v":366.41719828}]},{"c":[{"v":"19"},{"v":375.987390816}]},{"c":[{"v":"19"},{"v":374.044147928}]},{"c":[{"v":"19"},{"v":381.106150912}]},{"c":[{"v":"19"},{"v":392.780997976}]},{"c":[{"v":"19"},{"v":395.307043752}]},{"c":[{"v":"19"},{"v":385.613848696}]},{"c":[{"v":"20"},{"v":383.22917828}]},{"c":[{"v":"20"},{"v":392.623834336}]},{"c":[{"v":"20"},{"v":401.673709072}]},{"c":[{"v":"20"},{"v":403.670875872}]},{"c":[{"v":"20"},{"v":409.717403224}]},{"c":[{"v":"20"},{"v":410.40438928}]},{"c":[{"v":"20"},{"v":411.43729388}]},{"c":[{"v":"20"},{"v":414.925629904}]},{"c":[{"v":"20"},{"v":413.573216216}]},{"c":[{"v":"20"},{"v":411.31626784}]},{"c":[{"v":"20"},{"v":410.055672952}]},{"c":[{"v":"20"},{"v":411.067856184}]},{"c":[{"v":"21"},{"v":396.511147728}]},{"c":[{"v":"21"},{"v":396.520910528}]},{"c":[{"v":"21"},{"v":392.115261992}]},{"c":[{"v":"21"},{"v":392.318269024}]},{"c":[{"v":"21"},{"v":385.23977924}]},{"c":[{"v":"21"},{"v":386.457404736}]},{"c":[{"v":"21"},{"v":377.245925304}]},{"c":[{"v":"21"},{"v":371.092132056}]},{"c":[{"v":"21"},{"v":364.513660248}]},{"c":[{"v":"21"},{"v":356.452418208}]},{"c":[{"v":"21"},{"v":354.477989744}]},{"c":[{"v":"21"},{"v":350.934794488}]},{"c":[{"v":"22"},{"v":346.973776528}]},{"c":[{"v":"22"},{"v":338.553044024}]},{"c":[{"v":"22"},{"v":331.247622568}]},{"c":[{"v":"22"},{"v":327.674186664}]},{"c":[{"v":"22"},{"v":324.050471232}]},{"c":[{"v":"22"},{"v":314.838007448}]},{"c":[{"v":"22"},{"v":306.039755448}]},{"c":[{"v":"22"},{"v":303.44614156}]},{"c":[{"v":"22"},{"v":295.713026928}]},{"c":[{"v":"22"},{"v":289.1253494}]},{"c":[{"v":"22"},{"v":282.35042652}]},{"c":[{"v":"22"},{"v":274.930605752}]},{"c":[{"v":"23"},{"v":267.35436212}]},{"c":[{"v":"23"},{"v":262.613271432}]},{"c":[{"v":"23"},{"v":253.015483992}]},{"c":[{"v":"23"},{"v":243.162665688}]},{"c":[{"v":"23"},{"v":237.34979296}]},{"c":[{"v":"23"},{"v":229.495049496}]},{"c":[{"v":"23"},{"v":224.493356968}]},{"c":[{"v":"23"},{"v":219.182942656}]},{"c":[{"v":"23"},{"v":213.842643432}]},{"c":[{"v":"23"},{"v":204.296707208}]},{"c":[{"v":"23"},{"v":199.76260952}]},{"c":[{"v":"23"},{"v":192.724111896}]},{"c":[{"v":"00"},{"v":186.957568792}]},{"c":[{"v":"00"},{"v":183.322705024}]},{"c":[{"v":"00"},{"v":175.850124528}]},{"c":[{"v":"00"},{"v":170.76044028}]},{"c":[{"v":"00"},{"v":165.764135224}]},{"c":[{"v":"00"},{"v":158.627719448}]},{"c":[{"v":"00"},{"v":153.240423248}]},{"c":[{"v":"00"},{"v":148.121105304}]},{"c":[{"v":"00"},{"v":144.702818584}]},{"c":[{"v":"00"},{"v":139.819915144}]},{"c":[{"v":"00"},{"v":135.180148344}]},{"c":[{"v":"00"},{"v":131.95862156}]},{"c":[{"v":"01"},{"v":126.927435496}]},{"c":[{"v":"01"},{"v":126.56567044}]},{"c":[{"v":"01"},{"v":122.590863456}]},{"c":[{"v":"01"},{"v":119.19713304}]},{"c":[{"v":"01"},{"v":116.353088536}]},{"c":[{"v":"01"},{"v":114.582423832}]},{"c":[{"v":"01"},{"v":113.230783216}]},{"c":[{"v":"01"},{"v":110.042032224}]},{"c":[{"v":"01"},{"v":104.854096264}]},{"c":[{"v":"01"},{"v":101.285517096}]},{"c":[{"v":"01"},{"v":99.81008712}]},{"c":[{"v":"01"},{"v":98.761620768}]},{"c":[{"v":"01"},{"v":98.747779472}]},{"c":[{"v":"02"},{"v":96.755434792}]}]}