{"cols":[{"type":"string"},{"type":"number"}],"rows":[{"c":[{"v":"20"},{"v":8.086906152}]},{"c":[{"v":"20"},{"v":8.214453848}]},{"c":[{"v":"20"},{"v":8.17622064}]},{"c":[{"v":"20"},{"v":8.19590912}]},{"c":[{"v":"20"},{"v":8.223527688}]},{"c":[{"v":"20"},{"v":8.332875992}]},{"c":[{"v":"20"},{"v":8.273022984}]},{"c":[{"v":"20"},{"v":8.183356456}]},{"c":[{"v":"20"},{"v":8.157433984}]},{"c":[{"v":"20"},{"v":8.309220192}]},{"c":[{"v":"20"},{"v":8.228337288}]},{"c":[{"v":"21"},{"v":8.518832408}]},{"c":[{"v":"21"},{"v":8.617127752}]},{"c":[{"v":"21"},{"v":8.622197936}]},{"c":[{"v":"21"},{"v":8.59084976}]},{"c":[{"v":"21"},{"v":8.71970252}]},{"c":[{"v":"21"},{"v":8.333541944}]},{"c":[{"v":"21"},{"v":8.2942274}]},{"c":[{"v":"21"},{"v":7.993696608}]},{"c":[{"v":"21"},{"v":7.927809152}]},{"c":[{"v":"21"},{"v":8.0003534}]},{"c":[{"v":"21"},{"v":7.883826648}]},{"c":[{"v":"21"},{"v":7.793919048}]},{"c":[{"v":"22"},{"v":7.60366792}]},{"c":[{"v":"22"},{"v":7.487887608}]},{"c":[{"v":"22"},{"v":7.303276008}]},{"c":[{"v":"22"},{"v":7.392135088}]},{"c":[{"v":"22"},{"v":7.235642384}]},{"c":[{"v":"22"},{"v":7.184179208}]},{"c":[{"v":"22"},{"v":6.889558744}]},{"c":[{"v":"22"},{"v":6.997642296}]},{"c":[{"v":"22"},{"v":6.884378936}]},{"c":[{"v":"22"},{"v":6.7975382}]},{"c":[{"v":"22"},{"v":6.616953608}]},{"c":[{"v":"22"},{"v":6.376056208}]},{"c":[{"v":"23"},{"v":6.409560528}]},{"c":[{"v":"23"},{"v":6.27809172}]},{"c":[{"v":"23"},{"v":6.123962072}]},{"c":[{"v":"23"},{"v":6.216227272}]},{"c":[{"v":"23"},{"v":5.94483016}]},{"c":[{"v":"23"},{"v":5.744969912}]},{"c":[{"v":"23"},{"v":5.569904432}]},{"c":[{"v":"23"},{"v":5.651564624}]},{"c":[{"v":"23"},{"v":5.680678624}]},{"c":[{"v":"23"},{"v":5.354086536}]},{"c":[{"v":"23"},{"v":5.313681424}]},{"c":[{"v":"23"},{"v":5.153096184}]},{"c":[{"v":"00"},{"v":5.252610648}]},{"c":[{"v":"00"},{"v":5.163355784}]},{"c":[{"v":"00"},{"v":5.231507032}]},{"c":[{"v":"00"},{"v":5.027393064}]},{"c":[{"v":"00"},{"v":4.958020424}]},{"c":[{"v":"00"},{"v":4.679784608}]},{"c":[{"v":"00"},{"v":4.509761368}]},{"c":[{"v":"00"},{"v":4.616602008}]},{"c":[{"v":"00"},{"v":4.366347928}]},{"c":[{"v":"00"},{"v":4.30763268}]},{"c":[{"v":"00"},{"v":4.206546072}]},{"c":[{"v":"00"},{"v":4.136369544}]},{"c":[{"v":"01"},{"v":4.016283512}]},{"c":[{"v":"01"},{"v":4.223839696}]},{"c":[{"v":"01"},{"v":4.382677472}]},{"c":[{"v":"01"},{"v":4.370686248}]},{"c":[{"v":"01"},{"v":4.371319136}]},{"c":[{"v":"01"},{"v":4.411675824}]},{"c":[{"v":"01"},{"v":4.263407232}]},{"c":[{"v":"01"},{"v":4.21092464}]},{"c":[{"v":"01"},{"v":4.18375012}]},{"c":[{"v":"01"},{"v":4.117112032}]},{"c":[{"v":"01"},{"v":4.068435664}]},{"c":[{"v":"01"},{"v":3.94227696}]},{"c":[{"v":"02"},{"v":3.96202336}]},{"c":[{"v":"02"},{"v":3.893347544}]},{"c":[{"v":"02"},{"v":3.829948912}]},{"c":[{"v":"02"},{"v":3.7842542}]},{"c":[{"v":"02"},{"v":3.892321464}]},{"c":[{"v":"02"},{"v":3.765193968}]},{"c":[{"v":"02"},{"v":3.802557504}]},{"c":[{"v":"02"},{"v":3.724923624}]},{"c":[{"v":"02"},{"v":3.812597216}]},{"c":[{"v":"02"},{"v":3.747466536}]},{"c":[{"v":"02"},{"v":3.66762844}]},{"c":[{"v":"02"},{"v":3.745461256}]},{"c":[{"v":"03"},{"v":3.655198096}]},{"c":[{"v":"03"},{"v":3.68339068}]},{"c":[{"v":"03"},{"v":3.783062016}]},{"c":[{"v":"03"},{"v":3.654926888}]},{"c":[{"v":"03"},{"v":3.855926208}]},{"c":[{"v":"03"},{"v":3.84521508}]},{"c":[{"v":"03"},{"v":3.717614584}]},{"c":[{"v":"03"},{"v":3.87734464}]},{"c":[{"v":"03"},{"v":3.878339536}]},{"c":[{"v":"03"},{"v":3.711831592}]},{"c":[{"v":"03"},{"v":3.79530596}]},{"c":[{"v":"03"},{"v":3.813136008}]},{"c":[{"v":"04"},{"v":3.7495566}]},{"c":[{"v":"04"},{"v":3.8235724}]},{"c":[{"v":"04"},{"v":3.76222868}]},{"c":[{"v":"04"},{"v":3.709071232}]},{"c":[{"v":"04"},{"v":3.737592456}]},{"c":[{"v":"04"},{"v":3.696889488}]},{"c":[{"v":"04"},{"v":3.7375178}]},{"c":[{"v":"04"},{"v":3.92916988}]},{"c":[{"v":"04"},{"v":3.837904208}]},{"c":[{"v":"04"},{"v":3.744689688}]},{"c":[{"v":"04"},{"v":3.714074776}]},{"c":[{"v":"04"},{"v":3.773884632}]},{"c":[{"v":"05"},{"v":3.765146816}]},{"c":[{"v":"05"},{"v":3.874725296}]},{"c":[{"v":"05"},{"v":3.766149136}]},{"c":[{"v":"05"},{"v":3.734119}]},{"c":[{"v":"05"},{"v":3.872273488}]},{"c":[{"v":"05"},{"v":3.69428528}]},{"c":[{"v":"05"},{"v":3.555080008}]},{"c":[{"v":"05"},{"v":3.719761256}]},{"c":[{"v":"05"},{"v":3.865018696}]},{"c":[{"v":"05"},{"v":3.786171872}]},{"c":[{"v":"05"},{"v":3.835990992}]},{"c":[{"v":"05"},{"v":3.8959092}]},{"c":[{"v":"06"},{"v":3.997510864}]},{"c":[{"v":"06"},{"v":4.065894496}]},{"c":[{"v":"06"},{"v":4.030604512}]},{"c":[{"v":"06"},{"v":4.014925112}]},{"c":[{"v":"06"},{"v":4.088829976}]},{"c":[{"v":"06"},{"v":4.339796208}]},{"c":[{"v":"06"},{"v":3.946191048}]},{"c":[{"v":"06"},{"v":4.103426016}]},{"c":[{"v":"06"},{"v":4.071650096}]},{"c":[{"v":"06"},{"v":4.007735264}]},{"c":[{"v":"06"},{"v":4.210174808}]},{"c":[{"v":"06"},{"v":4.33792976}]},{"c":[{"v":"07"},{"v":4.325172816}]},{"c":[{"v":"07"},{"v":4.428469784}]},{"c":[{"v":"07"},{"v":4.409134824}]},{"c":[{"v":"07"},{"v":4.612139792}]},{"c":[{"v":"07"},{"v":4.42742232}]},{"c":[{"v":"07"},{"v":4.720875992}]},{"c":[{"v":"07"},{"v":4.786228752}]},{"c":[{"v":"07"},{"v":4.8172772}]},{"c":[{"v":"07"},{"v":4.982969792}]},{"c":[{"v":"07"},{"v":5.0585092}]},{"c":[{"v":"07"},{"v":5.031295528}]},{"c":[{"v":"07"},{"v":5.04708316}]},{"c":[{"v":"08"},{"v":5.016357712}]},{"c":[{"v":"08"},{"v":5.165591456}]},{"c":[{"v":"08"},{"v":5.324035512}]},{"c":[{"v":"08"},{"v":5.45363168}]},{"c":[{"v":"08"},{"v":5.501083864}]},{"c":[{"v":"08"},{"v":5.674507368}]},{"c":[{"v":"08"},{"v":5.239999632}]},{"c":[{"v":"08"},{"v":5.36250524}]},{"c":[{"v":"08"},{"v":5.565447568}]},{"c":[{"v":"08"},{"v":5.504377768}]},{"c":[{"v":"08"},{"v":5.787158864}]},{"c":[{"v":"08"},{"v":5.61174712}]},{"c":[{"v":"09"},{"v":5.569827168}]},{"c":[{"v":"09"},{"v":5.521533984}]},{"c":[{"v":"09"},{"v":5.731180048}]},{"c":[{"v":"09"},{"v":5.804529288}]},{"c":[{"v":"09"},{"v":5.65516328}]},{"c":[{"v":"09"},{"v":5.5185752}]},{"c":[{"v":"09"},{"v":5.66557732}]},{"c":[{"v":"09"},{"v":5.79285192}]},{"c":[{"v":"09"},{"v":5.7899702}]},{"c":[{"v":"09"},{"v":5.933850328}]},{"c":[{"v":"09"},{"v":6.064837704}]},{"c":[{"v":"09"},{"v":5.89619904}]},{"c":[{"v":"10"},{"v":5.996064288}]},{"c":[{"v":"10"},{"v":6.027930464}]},{"c":[{"v":"10"},{"v":6.057447408}]},{"c":[{"v":"10"},{"v":6.020186552}]},{"c":[{"v":"10"},{"v":5.96805048}]},{"c":[{"v":"10"},{"v":5.860349024}]},{"c":[{"v":"10"},{"v":6.13480588}]},{"c":[{"v":"10"},{"v":6.018500968}]},{"c":[{"v":"10"},{"v":5.92160108}]},{"c":[{"v":"10"},{"v":5.923849808}]},{"c":[{"v":"10"},{"v":5.821359432}]},{"c":[{"v":"10"},{"v":5.908645624}]},{"c":[{"v":"11"},{"v":5.893424264}]},{"c":[{"v":"11"},{"v":6.048977192}]},{"c":[{"v":"11"},{"v":6.149813968}]},{"c":[{"v":"11"},{"v":6.060715224}]},{"c":[{"v":"11"},{"v":5.925383952}]},{"c":[{"v":"11"},{"v":6.003788904}]},{"c":[{"v":"11"},{"v":5.962993744}]},{"c":[{"v":"11"},{"v":5.907692224}]},{"c":[{"v":"11"},{"v":5.98174092}]},{"c":[{"v":"11"},{"v":6.166127368}]},{"c":[{"v":"11"},{"v":6.095357456}]},{"c":[{"v":"11"},{"v":6.084189224}]},{"c":[{"v":"12"},{"v":6.161300392}]},{"c":[{"v":"12"},{"v":6.076778128}]},{"c":[{"v":"12"},{"v":6.041811936}]},{"c":[{"v":"12"},{"v":6.161859304}]},{"c":[{"v":"12"},{"v":6.066210136}]},{"c":[{"v":"12"},{"v":6.060710264}]},{"c":[{"v":"12"},{"v":6.030093512}]},{"c":[{"v":"12"},{"v":6.09902276}]},{"c":[{"v":"12"},{"v":6.171847712}]},{"c":[{"v":"12"},{"v":6.156506072}]},{"c":[{"v":"12"},{"v":6.21279984}]},{"c":[{"v":"12"},{"v":6.104417568}]},{"c":[{"v":"13"},{"v":6.157004872}]},{"c":[{"v":"13"},{"v":5.962058672}]},{"c":[{"v":"13"},{"v":6.145343232}]},{"c":[{"v":"13"},{"v":6.032012536}]},{"c":[{"v":"13"},{"v":6.220425952}]},{"c":[{"v":"13"},{"v":6.132160328}]},{"c":[{"v":"13"},{"v":6.166449384}]},{"c":[{"v":"13"},{"v":6.127826368}]},{"c":[{"v":"13"},{"v":6.262126592}]},{"c":[{"v":"13"},{"v":6.217072352}]},{"c":[{"v":"13"},{"v":6.452200408}]},{"c":[{"v":"13"},{"v":6.299227296}]},{"c":[{"v":"14"},{"v":6.243011304}]},{"c":[{"v":"14"},{"v":6.3731482}]},{"c":[{"v":"14"},{"v":6.23351004}]},{"c":[{"v":"14"},{"v":6.23081368}]},{"c":[{"v":"14"},{"v":6.265118832}]},{"c":[{"v":"14"},{"v":6.159443024}]},{"c":[{"v":"14"},{"v":6.407627776}]},{"c":[{"v":"14"},{"v":6.509137856}]},{"c":[{"v":"14"},{"v":6.590259152}]},{"c":[{"v":"14"},{"v":6.44709216}]},{"c":[{"v":"14"},{"v":6.575006968}]},{"c":[{"v":"14"},{"v":6.757388288}]},{"c":[{"v":"15"},{"v":7.074194472}]},{"c":[{"v":"15"},{"v":7.074518784}]},{"c":[{"v":"15"},{"v":6.559925808}]},{"c":[{"v":"15"},{"v":6.821522152}]},{"c":[{"v":"15"},{"v":6.669103512}]},{"c":[{"v":"15"},{"v":6.87790384}]},{"c":[{"v":"15"},{"v":6.975043336}]},{"c":[{"v":"15"},{"v":6.7547522}]},{"c":[{"v":"15"},{"v":6.585625496}]},{"c":[{"v":"15"},{"v":6.77614296}]},{"c":[{"v":"15"},{"v":6.9667488}]},{"c":[{"v":"15"},{"v":6.902518384}]},{"c":[{"v":"16"},{"v":6.860043424}]},{"c":[{"v":"16"},{"v":6.95437056}]},{"c":[{"v":"16"},{"v":7.101790224}]},{"c":[{"v":"16"},{"v":7.098861344}]},{"c":[{"v":"16"},{"v":7.099134264}]},{"c":[{"v":"16"},{"v":6.981634408}]},{"c":[{"v":"16"},{"v":6.990653512}]},{"c":[{"v":"16"},{"v":7.111893048}]},{"c":[{"v":"16"},{"v":7.318796152}]},{"c":[{"v":"16"},{"v":7.211592656}]},{"c":[{"v":"16"},{"v":7.021507496}]},{"c":[{"v":"16"},{"v":6.90851432}]},{"c":[{"v":"17"},{"v":6.963450592}]},{"c":[{"v":"17"},{"v":7.17644628}]},{"c":[{"v":"17"},{"v":7.195058464}]},{"c":[{"v":"17"},{"v":7.126325832}]},{"c":[{"v":"17"},{"v":7.272505728}]},{"c":[{"v":"17"},{"v":7.334238432}]},{"c":[{"v":"17"},{"v":7.25280956}]},{"c":[{"v":"17"},{"v":7.122727664}]},{"c":[{"v":"17"},{"v":7.064912808}]},{"c":[{"v":"17"},{"v":7.525838552}]},{"c":[{"v":"17"},{"v":7.479545144}]},{"c":[{"v":"17"},{"v":7.33351752}]},{"c":[{"v":"18"},{"v":7.2856802}]},{"c":[{"v":"18"},{"v":7.498100264}]},{"c":[{"v":"18"},{"v":7.541966712}]},{"c":[{"v":"18"},{"v":7.73335744}]},{"c":[{"v":"18"},{"v":7.277276576}]},{"c":[{"v":"18"},{"v":6.254111856}]},{"c":[{"v":"18"},{"v":6.324376224}]},{"c":[{"v":"18"},{"v":6.208282088}]},{"c":[{"v":"18"},{"v":6.173943104}]},{"c":[{"v":"18"},{"v":6.357139544}]},{"c":[{"v":"18"},{"v":6.224479648}]},{"c":[{"v":"18"},{"v":7.23151864}]},{"c":[{"v":"19"},{"v":7.34692416}]},{"c":[{"v":"19"},{"v":7.45257964}]},{"c":[{"v":"19"},{"v":7.538167528}]},{"c":[{"v":"19"},{"v":7.634828912}]},{"c":[{"v":"19"},{"v":7.615285528}]},{"c":[{"v":"19"},{"v":7.729948488}]},{"c":[{"v":"19"},{"v":7.776261832}]},{"c":[{"v":"19"},{"v":7.84738536}]},{"c":[{"v":"19"},{"v":7.957390256}]},{"c":[{"v":"19"},{"v":8.002403624}]},{"c":[{"v":"19"},{"v":8.2506958}]},{"c":[{"v":"19"},{"v":7.596394336}]},{"c":[{"v":"20"},{"v":7.177898832}]},{"c":[{"v":"20"},{"v":7.275147512}]},{"c":[{"v":"20"},{"v":6.993726152}]},{"c":[{"v":"20"},{"v":7.096533168}]},{"c":[{"v":"20"},{"v":7.082538696}]},{"c":[{"v":"20"},{"v":8.258696664}]},{"c":[{"v":"20"},{"v":8.709988592}]},{"c":[{"v":"20"},{"v":8.624399912}]},{"c":[{"v":"20"},{"v":9.055700016}]},{"c":[{"v":"20"},{"v":9.10426548}]},{"c":[{"v":"20"},{"v":9.043922008}]},{"c":[{"v":"20"},{"v":8.832563624}]},{"c":[{"v":"21"},{"v":8.642335096}]},{"c":[{"v":"21"},{"v":8.438480448}]},{"c":[{"v":"21"},{"v":8.100028696}]},{"c":[{"v":"21"},{"v":8.2657184}]},{"c":[{"v":"21"},{"v":8.457774488}]},{"c":[{"v":"21"},{"v":8.682933128}]},{"c":[{"v":"21"},{"v":8.530900704}]},{"c":[{"v":"21"},{"v":8.154265504}]},{"c":[{"v":"21"},{"v":8.242012096}]},{"c":[{"v":"21"},{"v":8.120481864}]},{"c":[{"v":"21"},{"v":7.924268592}]},{"c":[{"v":"21"},{"v":7.834760904}]},{"c":[{"v":"21"},{"v":7.834168984}]},{"c":[{"v":"22"},{"v":8.041404552}]}]}